Workbook
Name UPDATE: 'Data Sheet'!$E$1

Sheet Data Sheet
A1: COMPANY NAME | B1: INFOSYS LTD | E1: =IF(B2<>B3, "A NEW VERSION OF THE WORKSHEET IS AVAILABLE", "")
A2: LATEST VERSION | B2: 2.1 | E2: PLEASE DO NOT MAKE ANY CHANGES TO THIS SHEET
A3: CURRENT VERSION | B3: 2.1
A5: META
A6: Number of shares | B6: =IF(B9>0, B9/B8, 0) -> 405.46238
A7: Face Value | B7: 5
A8: Current Price | B8: 1161.2
A9: Market Capitalization | B9: 470822.91
A15: PROFIT & LOSS
A16: Report Date | B16: 42825 | C16: 43190 | D16: 43555 | E16: 43921 | F16: 44286 | G16: 44651 | H16: 45016 | I16: 45382 | J16: 45747 | K16: 46112
A17: Sales | B17: 68484 | C17: 70522 | D17: 82675 | E17: 90791 | F17: 100472 | G17: 121641 | H17: 146767 | I17: 153670 | J17: 162990 | K17: 178650
A18: Raw Material Cost
A19: Change in Inventory
A20: Power and Fuel | B20: 228 | C20: 207 | D20: 221 | E20: 229 | F20: 143 | G20: 132 | H20: 176 | I20: 199 | J20: 222 | K20: 223
A21: Other Mfr. Exp | B21: 6712 | C21: 7286 | D21: 9902 | E21: 11086 | F21: 12800 | G21: 20690 | H21: 26330 | I21: 27195 | J21: 30395 | K21: 32922
A22: Employee Cost | B22: 37669 | C22: 38902 | D22: 45323 | E22: 50895 | F22: 55547 | G22: 63997 | H22: 78374 | I22: 82636 | J22: 85968 | K22: 95112
A23: Selling and admin | B23: 4584 | C23: 4585 | D23: 5553 | E23: 5375 | F23: 3194 | G23: 4305 | H23: 5300 | I23: 5705 | J23: 6039 | K23: 6784
A24: Other Expenses | B24: 687 | C24: 720 | D24: 1506 | E24: 939 | F24: 899 | G24: 1026 | H24: 1457 | I24: 1510 | J24: 1130 | K24: 1329
A25: Other Income | B25: 3050 | C25: 3311 | D25: 2882 | E25: 2803 | F25: 2201 | G25: 2295 | H25: 2701 | I25: 4711 | J25: 3600 | K25: 3033
A26: Depreciation | B26: 1703 | C26: 1863 | D26: 2011 | E26: 2893 | F26: 3267 | G26: 3476 | H26: 4225 | I26: 4678 | J26: 4812 | K26: 4902
A27: Interest | E27: 170 | F27: 195 | G27: 200 | H27: 284 | I27: 470 | J27: 416 | K27: 416
A28: Profit before tax | B28: 19951 | C28: 20270 | D28: 21041 | E28: 22007 | F28: 26628 | G28: 30110 | H28: 33322 | I28: 35988 | J28: 37608 | K28: 39995
A29: Tax | B29: 5598 | C29: 4241 | D29: 5631 | E29: 5368 | F29: 7205 | G29: 7964 | H29: 9214 | I29: 9740 | J29: 10858 | K29: 10521
A30: Net profit | B30: 14353 | C30: 16029 | D30: 15404 | E30: 16594 | F30: 19351 | G30: 22110 | H30: 24095 | I30: 26233 | J30: 26713 | K30: 29440
A31: Dividend Amount | B31: 5891.6 | C31: 9465.6 | D31: 9222.5 | E31: 7427 | F31: 11469.6 | G31: 13007.6 | H31: 14069.2 | I31: 19053.2 | J31: 17827.8 | K31: 19430.4
A32: ='Historical Financial Statement'!B10 -> EBITDA | B32: ='Historical Financial Statement'!C10 -> 18604 | C32: ='Historical Financial Statement'!D10 -> 18822 | D32: ='Historical Financial Statement'!E10 -> 20170 | E32: ='Historical Financial Statement'!F10 -> 22267 | F32: ='Historical Financial Statement'!G10 -> 27889 | G32: ='Historical Financial Statement'!H10 -> 31491 | H32: ='Historical Financial Statement'!I10 -> 35130 | ... K32: ='Historical Financial Statement'!L10 -> 42280
A33: ='Historical Financial Statement'!B14 -> EBIT | B33: ='Historical Financial Statement'!C14 -> 16901 | C33: ='Historical Financial Statement'!D14 -> 16959 | D33: ='Historical Financial Statement'!E14 -> 18159 | E33: ='Historical Financial Statement'!F14 -> 19374 | F33: ='Historical Financial Statement'!G14 -> 24622 | G33: ='Historical Financial Statement'!H14 -> 28015 | H33: ='Historical Financial Statement'!I14 -> 30905 | ... K33: ='Historical Financial Statement'!L14 -> 37378
A40: Quarters
A41: Report Date | B41: 45382 | C41: 45473 | D41: 45565 | E41: 45657 | F41: 45747 | G41: 45838 | H41: 45930 | I41: 46022 | J41: 46112 | K41: 46203
A42: Sales | B42: 37923 | C42: 39315 | D42: 40986 | E42: 41764 | F42: 40925 | G42: 42279 | H42: 44490 | I42: 45479 | J42: 46402 | K42: 48211
A43: Expenses | B43: 29139 | C43: 29878 | D43: 31177 | E43: 31649 | F43: 31051 | G43: 32336 | H43: 33955 | I43: 34845 | J43: 35235 | K43: 36802
A44: Other Income | B44: 2729 | C44: 838 | D44: 712 | E44: 859 | F44: 1190 | G44: 1042 | H44: 982 | I44: -150 | J44: 1159 | K44: 984
A45: Depreciation | B45: 1163 | C45: 1149 | D45: 1160 | E45: 1203 | F45: 1299 | G45: 1140 | H45: 1182 | I45: 1155 | J45: 1424 | K45: 1246
A46: Interest | B46: 110 | C46: 105 | D46: 108 | E46: 101 | F46: 102 | G46: 105 | H46: 106 | I46: 100 | J46: 105 | K46: 119
A47: Profit before tax | B47: 10240 | C47: 9021 | D47: 9253 | E47: 9670 | F47: 9663 | G47: 9740 | H47: 10229 | I47: 9229 | J47: 10797 | K47: 11028
A48: Tax | B48: 2265 | C48: 2647 | D48: 2737 | E48: 2848 | F48: 2625 | G48: 2816 | H48: 2854 | I48: 2563 | J48: 2288 | K48: 3253
A49: Net profit | B49: 7969 | C49: 6368 | D49: 6506 | E49: 6806 | F49: 7033 | G49: 6921 | H49: 7364 | I49: 6654 | J49: 8501 | K49: 7769
A50: Operating Profit | B50: 8784 | C50: 9437 | D50: 9809 | E50: 10115 | F50: 9874 | G50: 9943 | H50: 10535 | I50: 10634 | J50: 11167 | K50: 11409
A55: BALANCE SHEET
A56: Report Date | B56: 42825 | C56: 43190 | D56: 43555 | E56: 43921 | F56: 44286 | G56: 44651 | H56: 45016 | I56: 45382 | J56: 45747 | K56: 46112
A57: Equity Share Capital | B57: 1144 | C57: 1088 | D57: 2170 | E57: 2122 | F57: 2124 | G57: 2098 | H57: 2069 | I57: 2071 | J57: 2073 | K57: 2024
A58: Reserves | B58: 67838 | C58: 63835 | D58: 62778 | E58: 63328 | F58: 74227 | G58: 73252 | H58: 73338 | I58: 86045 | J58: 93745 | K58: 90828
A59: Borrowings | E59: 4633 | F59: 5325 | G59: 5474 | H59: 8299 | I59: 8359 | J59: 8227 | K59: 9176
A60: Other Liabilities | B60: 14166 | C60: 14426 | D60: 19118 | E60: 21717 | F60: 25835 | G60: 35905 | H60: 40890 | I60: 39545 | J60: 43750 | K60: 52260
A61: Total | B61: 83148 | C61: 79349 | D61: 84066 | E61: 91800 | F61: 107511 | G61: 116729 | H61: 124596 | I61: 136020 | J61: 147795 | K61: 154288
A62: Net Block | B62: 14179 | C62: 12574 | D62: 15710 | E62: 23789 | F62: 25505 | G62: 25800 | H62: 29225 | I62: 27622 | J62: 30961 | K62: 33770
A63: Capital Work in Progress | B63: 1365 | C63: 1606 | D63: 1388 | E63: 954 | F63: 922 | G63: 416 | H63: 288 | I63: 293 | J63: 814 | K63: 526
A64: Investments | B64: 16423 | C64: 12163 | D64: 11261 | E64: 8792 | F64: 14205 | G64: 20324 | H64: 19478 | I64: 24623 | J64: 23541 | K64: 21880
A65: Other Assets | B65: 51181 | C65: 53006 | D65: 55707 | E65: 58265 | F65: 66879 | G65: 70189 | H65: 75605 | I65: 83482 | J65: 92479 | K65: 98112
A66: Total | B66: 83148 | C66: 79349 | D66: 84066 | E66: 91800 | F66: 107511 | G66: 116729 | H66: 124596 | I66: 136020 | J66: 147795 | K66: 154288
A67: Receivables | B67: 12322 | C67: 13142 | D67: 14827 | E67: 18487 | F67: 19294 | G67: 22698 | H67: 25424 | I67: 30193 | J67: 31158 | K67: 35234
A68: Inventory
A69: Cash & Bank | B69: 22625 | C69: 19818 | D69: 19568 | E69: 18649 | F69: 24714 | G69: 17472 | H69: 12173 | I69: 14786 | J69: 24455 | K69: 22201
A70: No. of Equity Shares | B70: 2285655150 | C70: 2173312301 | D70: 4335954462 | E70: 4240753210 | F70: 4245146114 | G70: 4193012929 | H70: 4136387925 | I70: 4139950635 | J70: 4143607528 | K70: 4046940812
A71: New Bonus Shares | D71: 2184191490
A72: Face value | B72: 5 | C72: 5 | D72: 5 | E72: 5 | F72: 5 | G72: 5 | H72: 5 | I72: 5 | J72: 5 | K72: 5
A74: Other Assets | B74: =B65-SUM(B67:B69) -> 16234 | C74: =C65-SUM(C67:C69) -> 20046 | D74: =D65-SUM(D67:D69) -> 21312 | E74: =E65-SUM(E67:E69) -> 21129 | F74: =F65-SUM(F67:F69) -> 22871 | G74: =G65-SUM(G67:G69) -> 30019 | H74: =H65-SUM(H67:H69) -> 38008 | I74: =I65-SUM(I67:I69) -> 38503 | ... K74: =K65-SUM(K67:K69) -> 40677
A80: CASH FLOW:
A81: Report Date | B81: 42825 | C81: 43190 | D81: 43555 | E81: 43921 | F81: 44286 | G81: 44651 | H81: 45016 | I81: 45382 | J81: 45747 | K81: 46112
A82: Cash from Operating Activity | B82: 11531 | C82: 13218 | D82: 14841 | E82: 17003 | F82: 23224 | G82: 23885 | H82: 22467 | I82: 25210 | J82: 35694 | K82: 33986
A83: Cash from Investing Activity | B83: -14664 | C83: 4533 | D83: -632 | E83: -331 | F83: -7373 | G83: -6485 | H83: -1071 | I83: -5093 | J83: -1864 | K83: 3546
A84: Cash from Financing Activity | B84: -6939 | C84: -20505 | D84: -14512 | E84: -17591 | F84: -9786 | G84: -24642 | H84: -26695 | I84: -17504 | J84: -24161 | K84: -39786
A85: Net Cash Flow | B85: -10072 | C85: -2754 | D85: -303 | E85: -919 | F85: 6065 | G85: -7242 | H85: -5299 | I85: 2613 | J85: 9669 | K85: -2254
A90: PRICE: | B90: 511.13 | C90: 565.9 | D90: 743.85 | E90: 641.5 | F90: 1368.05 | G90: 1906.85 | H90: 1427.95 | I90: 1498.05 | J90: 1570.65 | K90: 1250.6
A92: DERIVED:
A93: Adjusted Equity Shares in Cr | B93: 459.39 | C93: 436.82 | D93: 436.89 | E93: 425.9 | F93: 426.07 | G93: 420.67 | H93: 414.86 | I93: 415.09 | J93: 415.33 | K93: 405.56

Sheet Historical Financial Statement
A1: * | B1: ="Income Statement for "&'Data Sheet'!B1 -> Income Statement for INFOSYS LTD
B2: ='Data Sheet'!A16 -> Report Date | C2: ='Data Sheet'!B16 -> 42825 | D2: ='Data Sheet'!C16 -> 43190 | E2: ='Data Sheet'!D16 -> 43555 | F2: ='Data Sheet'!E16 -> 43921 | G2: ='Data Sheet'!F16 -> 44286 | H2: ='Data Sheet'!G16 -> 44651 | I2: ='Data Sheet'!H16 -> 45016 | ... L2: ='Data Sheet'!K16 -> 46112 | M2: =L2+365 -> 46477 | N2: =M2+365 -> 46842 | O2: =N2+365 -> 47207 | P2: =O2+365 -> 47572 | Q2: =P2+365 -> 47937
B3: ='Data Sheet'!A17 -> Sales | C3: ='Data Sheet'!B17 -> 68484 | D3: ='Data Sheet'!C17 -> 70522 | E3: ='Data Sheet'!D17 -> 82675 | F3: ='Data Sheet'!E17 -> 90791 | G3: ='Data Sheet'!F17 -> 100472 | H3: ='Data Sheet'!G17 -> 121641 | I3: ='Data Sheet'!H17 -> 146767 | ... L3: ='Data Sheet'!K17 -> 178650 | M3: =Calculation!M3 -> 196627.57 | N3: =Calculation!N3 -> 216414.22 | O3: =Calculation!O3 -> 238192.01 | P3: =Calculation!P3 -> 262161.3 | Q3: =Calculation!Q3 -> 288542.62
B4: COGS | C4: =SUM('Data Sheet'!B20:B22) -> 44609 | D4: =SUM('Data Sheet'!C20:C22) -> 46395 | E4: =SUM('Data Sheet'!D20:D22) -> 55446 | F4: =SUM('Data Sheet'!E20:E22) -> 62210 | G4: =SUM('Data Sheet'!F20:F22) -> 68490 | H4: =SUM('Data Sheet'!G20:G22) -> 84819 | I4: =SUM('Data Sheet'!H20:H22) -> 104880 | J4: =SUM('Data Sheet'!I20:I22) -> 110030 | ... L4: =SUM('Data Sheet'!K20:K22) -> 128257 | M4: =Calculation!M6 -> 135828.55 | N4: =Calculation!N6 -> 150349.94 | O4: =Calculation!O6 -> 166357.47 | P4: =Calculation!P6 -> 183825.99 | Q4: =Calculation!Q6 -> 202785.92
B5: Gross Profit | C5: =C3-C4 -> 23875 | D5: =D3-D4 -> 24127 | E5: =E3-E4 -> 27229 | F5: =F3-F4 -> 28581 | G5: =G3-G4 -> 31982 | H5: =H3-H4 -> 36822 | I5: =I3-I4 -> 41887 | J5: =J3-J4 -> 43640 | ... Q5: =Q3-Q4 -> 85756.699
B6: Gross Profit Margin | C6: =C5/C3 -> 0.34862158 | D6: =D5/D3 -> 0.34212019 | E6: =E5/E3 -> 0.32934986 | F6: =F5/F3 -> 0.31479993 | G6: =G5/G3 -> 0.31831754 | H6: =H5/H3 -> 0.30271043 | I6: =I5/I3 -> 0.28539794 | J6: =J5/J3 -> 0.28398516 | ... Q6: =Q5/Q3 -> 0.29720635
B8: ='Data Sheet'!A23 -> Selling and admin | C8: ='Data Sheet'!B23 -> 4584 | D8: ='Data Sheet'!C23 -> 4585 | E8: ='Data Sheet'!D23 -> 5553 | F8: ='Data Sheet'!E23 -> 5375 | G8: ='Data Sheet'!F23 -> 3194 | H8: ='Data Sheet'!G23 -> 4305 | I8: ='Data Sheet'!H23 -> 5300 | ... L8: ='Data Sheet'!K23 -> 6784 | M8: =Calculation!M10 -> 9315.4617 | N8: =Calculation!N10 -> 9829.5894 | O8: =Calculation!O10 -> 10352.007 | P8: =Calculation!P10 -> 10772.255 | Q8: =Calculation!Q10 -> 11333.667
B9: ='Data Sheet'!A24 -> Other Expenses | C9: ='Data Sheet'!B24 -> 687 | D9: ='Data Sheet'!C24 -> 720 | E9: ='Data Sheet'!D24 -> 1506 | F9: ='Data Sheet'!E24 -> 939 | G9: ='Data Sheet'!F24 -> 899 | H9: ='Data Sheet'!G24 -> 1026 | I9: ='Data Sheet'!H24 -> 1457 | ... L9: ='Data Sheet'!K24 -> 1329 | M9: =Calculation!M14 -> 1972.322 | N9: =Calculation!N14 -> 2170.7799 | O9: =Calculation!O14 -> 2384.9643 | P9: =Calculation!P14 -> 2409.9093 | Q9: =Calculation!Q14 -> 2619.2373
B10: EBITDA | C10: =C5-SUM(C8:C9) -> 18604 | D10: =D5-SUM(D8:D9) -> 18822 | E10: =E5-SUM(E8:E9) -> 20170 | F10: =F5-SUM(F8:F9) -> 22267 | G10: =G5-SUM(G8:G9) -> 27889 | H10: =H5-SUM(H8:H9) -> 31491 | I10: =I5-SUM(I8:I9) -> 35130 | J10: =J5-SUM(J8:J9) -> 36425 | ... Q10: =Q5-SUM(Q8:Q9) -> 71803.795
B11: EBITDA Margin | C11: =C10/C3 -> 0.27165469 | D11: =D10/D3 -> 0.26689544 | E11: =E10/E3 -> 0.24396734 | F11: =F10/F3 -> 0.24525559 | G11: =G10/G3 -> 0.27757982 | H11: =H10/H3 -> 0.25888475 | I11: =I10/I3 -> 0.23935898 | J11: =J10/J3 -> 0.2370339 | ... Q11: =Q10/Q3 -> 0.24884987
B13: ='Data Sheet'!A26 -> Depreciation | C13: ='Data Sheet'!B26 -> 1703 | D13: ='Data Sheet'!C26 -> 1863 | E13: ='Data Sheet'!D26 -> 2011 | F13: ='Data Sheet'!E26 -> 2893 | G13: ='Data Sheet'!F26 -> 3267 | H13: ='Data Sheet'!G26 -> 3476 | I13: ='Data Sheet'!H26 -> 4225 | ... L13: ='Data Sheet'!K26 -> 4902 | M13: =Calculation!M19 -> 4711.642 | N13: =Calculation!N19 -> 4763.7377 | O13: =Calculation!O19 -> 4733.8014 | P13: =Calculation!P19 -> 4813.7466 | Q13: =Calculation!Q19 -> 4946.5198
B14: EBIT | C14: =C10-C13 -> 16901 | D14: =D10-D13 -> 16959 | E14: =E10-E13 -> 18159 | F14: =F10-F13 -> 19374 | G14: =G10-G13 -> 24622 | H14: =H10-H13 -> 28015 | I14: =I10-I13 -> 30905 | J14: =J10-J13 -> 31747 | ... Q14: =Q10-Q13 -> 66857.275
B15: EBIT Margin | C15: =C14/C3 -> 0.24678757 | D15: =D14/D3 -> 0.24047815 | E15: =E14/E3 -> 0.21964318 | F15: =F14/F3 -> 0.2133912 | G15: =G14/G3 -> 0.2450633 | H15: =H14/H3 -> 0.23030886 | I15: =I14/I3 -> 0.21057186 | J15: =J14/J3 -> 0.20659205 | ... Q15: =Q14/Q3 -> 0.23170676
B17: ='Data Sheet'!A27 -> Interest | C17: ='Data Sheet'!B27 -> 0 | D17: ='Data Sheet'!C27 -> 0 | E17: ='Data Sheet'!D27 -> 0 | F17: ='Data Sheet'!E27 -> 170 | G17: ='Data Sheet'!F27 -> 195 | H17: ='Data Sheet'!G27 -> 200 | I17: ='Data Sheet'!H27 -> 284 | ... L17: ='Data Sheet'!K27 -> 416 | M17: =Calculation!M29 -> 271.79132 | N17: =Calculation!N29 -> 298.97046 | O17: =Calculation!O29 -> 328.8675 | P17: =Calculation!P29 -> 361.75425 | Q17: =Calculation!Q29 -> 364.25992
B18: ='Data Sheet'!A25 -> Other Income | C18: ='Data Sheet'!B25 -> 3050 | D18: ='Data Sheet'!C25 -> 3311 | E18: ='Data Sheet'!D25 -> 2882 | F18: ='Data Sheet'!E25 -> 2803 | G18: ='Data Sheet'!F25 -> 2201 | H18: ='Data Sheet'!G25 -> 2295 | I18: ='Data Sheet'!H25 -> 2701 | ... L18: ='Data Sheet'!K25 -> 3033 | M18: =Calculation!M36 -> 5625.8377 | N18: =Calculation!N36 -> 5847.3417 | O18: =Calculation!O36 -> 5961.0275 | P18: =Calculation!P36 -> 6303.0967 | Q18: =Calculation!Q36 -> 6740.2952
B19: EBT | C19: =SUM(C14,C18)-C17 -> 19951 | D19: =SUM(D14,D18)-D17 -> 20270 | E19: =SUM(E14,E18)-E17 -> 21041 | F19: =SUM(F14,F18)-F17 -> 22007 | G19: =SUM(G14,G18)-G17 -> 26628 | H19: =SUM(H14,H18)-H17 -> 30110 | I19: =SUM(I14,I18)-I17 -> 33322 | J19: =SUM(J14,J18)-J17 -> 35988 | ... Q19: =SUM(Q14,Q18)-Q17 -> 73233.31
B20: EBT Margin | C20: =C19/C3 -> 0.29132352 | D20: =D19/D3 -> 0.28742804 | E20: =E19/E3 -> 0.25450257 | F20: =F19/F3 -> 0.24239187 | G20: =G19/G3 -> 0.26502906 | H20: =H19/H3 -> 0.24753167 | I20: =I19/I3 -> 0.22704014 | J20: =J19/J3 -> 0.23419015 | ... Q20: =Q19/Q3 -> 0.25380413
B22: ='Data Sheet'!A29 -> Tax | C22: ='Data Sheet'!B29 -> 5598 | D22: ='Data Sheet'!C29 -> 4241 | E22: ='Data Sheet'!D29 -> 5631 | F22: ='Data Sheet'!E29 -> 5368 | G22: ='Data Sheet'!F29 -> 7205 | H22: ='Data Sheet'!G29 -> 7964 | I22: ='Data Sheet'!H29 -> 9214 | ... L22: ='Data Sheet'!K29 -> 10521 | M22: =Calculation!M41 -> 13217.314 | N22: =Calculation!N41 -> 14361.073 | O22: =Calculation!O41 -> 16024.434 | P22: =Calculation!P41 -> 17699.555 | Q22: =Calculation!Q41 -> 19725.456
B23: Net Profit | C23: =C19-C22 -> 14353 | D23: =D19-D22 -> 16029 | E23: =E19-E22 -> 15410 | F23: =F19-F22 -> 16639 | G23: =G19-G22 -> 19423 | H23: =H19-H22 -> 22146 | I23: =I19-I22 -> 24108 | J23: =J19-J22 -> 26248 | ... Q23: =Q19-Q22 -> 53507.855
B24: Net Profit Margin | C24: =C23/C3 -> 0.2095818 | D24: =D23/D3 -> 0.22729077 | E24: =E23/E3 -> 0.1863925 | F24: =F23/F3 -> 0.18326706 | G24: =G23/G3 -> 0.19331754 | H24: =H23/H3 -> 0.18206033 | I24: =I23/I3 -> 0.16426036 | J24: =J23/J3 -> 0.17080757 | ... Q24: =Q23/Q3 -> 0.18544177
A27: * | B27: ="Balance Sheet For "&'Data Sheet'!B1 -> Balance Sheet For INFOSYS LTD
B28: Shareholders Funds
B29: ='Data Sheet'!A57 -> Equity Share Capital | C29: ='Data Sheet'!B57 -> 1144 | D29: ='Data Sheet'!C57 -> 1088 | E29: ='Data Sheet'!D57 -> 2170 | F29: ='Data Sheet'!E57 -> 2122 | G29: ='Data Sheet'!F57 -> 2124 | H29: ='Data Sheet'!G57 -> 2098 | I29: ='Data Sheet'!H57 -> 2069 | ... L29: ='Data Sheet'!K57 -> 2024 | M29: =L29 -> 2024 | N29: =M29 -> 2024 | O29: =N29 -> 2024 | P29: =O29 -> 2024 | Q29: =P29 -> 2024
B30: ='Data Sheet'!A58 -> Reserves | C30: ='Data Sheet'!B58 -> 67838 | D30: ='Data Sheet'!C58 -> 63835 | E30: ='Data Sheet'!D58 -> 62778 | F30: ='Data Sheet'!E58 -> 63328 | G30: ='Data Sheet'!F58 -> 74227 | H30: ='Data Sheet'!G58 -> 73252 | I30: ='Data Sheet'!H58 -> 73338 | ... L30: ='Data Sheet'!K58 -> 90828 | M30: =Calculation!S14 -> 105689.07 | N30: =Calculation!T14 -> 121516.54 | O30: =Calculation!U14 -> 138075.35 | P30: =Calculation!V14 -> 157662.03 | Q30: =Calculation!W14 -> 179111.99
B31: Total Shareholers Funds | C31: =SUM(C29:C30) -> 68982 | D31: =SUM(D29:D30) -> 64923 | E31: =SUM(E29:E30) -> 64948 | F31: =SUM(F29:F30) -> 65450 | G31: =SUM(G29:G30) -> 76351 | H31: =SUM(H29:H30) -> 75350 | I31: =SUM(I29:I30) -> 75407 | J31: =SUM(J29:J30) -> 88116 | ... Q31: =SUM(Q29:Q30) -> 181135.99
B33: Non-Current Liabilities
B34: ='Data Sheet'!A59 -> Borrowings | C34: ='Data Sheet'!B59 -> 0 | D34: ='Data Sheet'!C59 -> 0 | E34: ='Data Sheet'!D59 -> 0 | F34: ='Data Sheet'!E59 -> 4633 | G34: ='Data Sheet'!F59 -> 5325 | H34: ='Data Sheet'!G59 -> 5474 | I34: ='Data Sheet'!H59 -> 8299 | ... L34: ='Data Sheet'!K59 -> 9176 | M34: =Calculation!S23 -> 9176 | N34: =Calculation!T23 -> 9176 | O34: =Calculation!U23 -> 9176 | P34: =Calculation!V23 -> 9176 | Q34: =Calculation!W23 -> 9176
B35: ='Data Sheet'!A60 -> Other Liabilities | C35: ='Data Sheet'!B60-SUM(C39:C40) -> 13799 | D35: ='Data Sheet'!C60-SUM(D39:D40) -> 13732 | E35: ='Data Sheet'!D60-SUM(E39:E40) -> 17463 | F35: ='Data Sheet'!E60-SUM(F39:F40) -> 18865 | G35: ='Data Sheet'!F60-SUM(G39:G40) -> 23190 | H35: ='Data Sheet'!G60-SUM(H39:H40) -> 31771 | I35: ='Data Sheet'!H60-SUM(I39:I40) -> 37025 | J35: ='Data Sheet'!I60-SUM(J39:J40) -> 35589 | ... L35: ='Data Sheet'!K60-SUM(L39:L40) -> 47516 | M35: =Calculation!M49 -> 45222.947 | N35: =Calculation!N49 -> 50390.531 | O35: =Calculation!O49 -> 56369.409 | P35: =Calculation!P49 -> 62708.562 | Q35: =Calculation!Q49 -> 69925.345
B36: Total Non-Current Liabilities | C36: =SUM(C34:C35) -> 13799 | D36: =SUM(D34:D35) -> 13732 | E36: =SUM(E34:E35) -> 17463 | F36: =SUM(F34:F35) -> 23498 | G36: =SUM(G34:G35) -> 28515 | H36: =SUM(H34:H35) -> 37245 | I36: =SUM(I34:I35) -> 45324 | J36: =SUM(J34:J35) -> 43948 | ... Q36: =SUM(Q34:Q35) -> 79101.345
B38: Current Liabilities
B39: ='Manual Data'!B36 -> Trade Payables | C39: ='Manual Data'!C36 -> 367 | D39: ='Manual Data'!D36 -> 694 | E39: ='Manual Data'!E36 -> 1655 | F39: ='Manual Data'!F36 -> 2852 | G39: ='Manual Data'!G36 -> 2645 | H39: ='Manual Data'!H36 -> 4134 | I39: ='Manual Data'!I36 -> 3865 | ... L39: ='Manual Data'!L36 -> 4744 | M39: =Calculation!M54 -> 4506.0732 | N39: =Calculation!N54 -> 5362.9041 | O39: =Calculation!O54 -> 6278.4267 | P39: =Calculation!P54 -> 7082.7691 | Q39: =Calculation!Q54 -> 7664.9531
B40: ='Manual Data'!B37 -> Advance from Customers | C40: ='Manual Data'!C37 -> 0 | D40: ='Manual Data'!D37 -> 0 | E40: ='Manual Data'!E37 -> 0 | F40: ='Manual Data'!F37 -> 0 | G40: ='Manual Data'!G37 -> 0 | H40: ='Manual Data'!H37 -> 0 | I40: ='Manual Data'!I37 -> 0 | ... L40: ='Manual Data'!L37 -> 0 | M40: =L40 -> 0 | N40: =M40 -> 0 | O40: =N40 -> 0 | P40: =O40 -> 0 | Q40: =P40 -> 0
B41: Total Current Liabilities | C41: =SUM(C39:C40) -> 367 | D41: =SUM(D39:D40) -> 694 | E41: =SUM(E39:E40) -> 1655 | F41: =SUM(F39:F40) -> 2852 | G41: =SUM(G39:G40) -> 2645 | H41: =SUM(H39:H40) -> 4134 | I41: =SUM(I39:I40) -> 3865 | J41: =SUM(J39:J40) -> 3956 | ... Q41: =SUM(Q39:Q40) -> 7664.9531
B43: Total Liabilities | C43: =SUM(C41,C36) -> 14166 | D43: =SUM(D41,D36) -> 14426 | E43: =SUM(E41,E36) -> 19118 | F43: =SUM(F41,F36) -> 26350 | G43: =SUM(G41,G36) -> 31160 | H43: =SUM(H41,H36) -> 41379 | I43: =SUM(I41,I36) -> 49189 | J43: =SUM(J41,J36) -> 47904 | ... Q43: =SUM(Q41,Q36) -> 86766.298
B45: Total Liabilities & Shareholer's Funds | C45: =SUM(C41,C36,C31) -> 83148 | D45: =SUM(D41,D36,D31) -> 79349 | E45: =SUM(E41,E36,E31) -> 84066 | F45: =SUM(F41,F36,F31) -> 91800 | G45: =SUM(G41,G36,G31) -> 107511 | H45: =SUM(H41,H36,H31) -> 116729 | I45: =SUM(I41,I36,I31) -> 124596 | J45: =SUM(J41,J36,J31) -> 136020 | ... Q45: =SUM(Q41,Q36,Q31) -> 267902.29
B47: Non-Current Assets
B48: ='Data Sheet'!A62 -> Net Block | C48: ='Data Sheet'!B62 -> 14179 | D48: ='Data Sheet'!C62 -> 12574 | E48: ='Data Sheet'!D62 -> 15710 | F48: ='Data Sheet'!E62 -> 23789 | G48: ='Data Sheet'!F62 -> 25505 | H48: ='Data Sheet'!G62 -> 25800 | I48: ='Data Sheet'!H62 -> 29225 | ... L48: ='Data Sheet'!K62 -> 33770 | M48: =Calculation!S7 -> 33664.389 | N48: =Calculation!T7 -> 33604.963 | O48: =Calculation!U7 -> 33891.802 | P48: =Calculation!V7 -> 34381.206 | Q48: =Calculation!W7 -> 34804.176
B49: ='Data Sheet'!A63 -> Capital Work in Progress | C49: ='Data Sheet'!B63 -> 1365 | D49: ='Data Sheet'!C63 -> 1606 | E49: ='Data Sheet'!D63 -> 1388 | F49: ='Data Sheet'!E63 -> 954 | G49: ='Data Sheet'!F63 -> 922 | H49: ='Data Sheet'!G63 -> 416 | I49: ='Data Sheet'!H63 -> 288 | ... L49: ='Data Sheet'!K63 -> 526 | M49: =Calculation!M66 -> 1572.295 | N49: =Calculation!N66 -> 1402.9594 | O49: =Calculation!O66 -> 1123.5487 | P49: =Calculation!P66 -> 949.9876 | Q49: =Calculation!Q66 -> 918.26848
B50: ='Data Sheet'!A64 -> Investments | C50: ='Data Sheet'!B64 -> 16423 | D50: ='Data Sheet'!C64 -> 12163 | E50: ='Data Sheet'!D64 -> 11261 | F50: ='Data Sheet'!E64 -> 8792 | G50: ='Data Sheet'!F64 -> 14205 | H50: ='Data Sheet'!G64 -> 20324 | I50: ='Data Sheet'!H64 -> 19478 | ... L50: ='Data Sheet'!K64 -> 21880 | M50: =Calculation!M62 -> 29762.378 | N50: =Calculation!N62 -> 30843.324 | O50: =Calculation!O62 -> 33233.679 | P50: =Calculation!P62 -> 36664.939 | Q50: =Calculation!Q62 -> 41595.806
B51: ='Data Sheet'!A65 -> Other Assets | C51: ='Data Sheet'!B65-SUM(C55:C57) -> 16234 | D51: ='Data Sheet'!C65-SUM(D55:D57) -> 20046 | E51: ='Data Sheet'!D65-SUM(E55:E57) -> 21312 | F51: ='Data Sheet'!E65-SUM(F55:F57) -> 21129 | G51: ='Data Sheet'!F65-SUM(G55:G57) -> 22871 | H51: ='Data Sheet'!G65-SUM(H55:H57) -> 30019 | I51: ='Data Sheet'!H65-SUM(I55:I57) -> 38008 | J51: ='Data Sheet'!I65-SUM(J55:J57) -> 38503 | ... L51: ='Data Sheet'!K65-SUM(L55:L57) -> 40677 | M51: =Calculation!M70 -> 48166.323 | N51: =Calculation!N70 -> 53184.578 | O51: =Calculation!O70 -> 57619.554 | P51: =Calculation!P70 -> 63001.592 | Q51: =Calculation!Q70 -> 69560.593
B52: Total Non-Current Assets | C52: =SUM(C48:C51) -> 48201 | D52: =SUM(D48:D51) -> 46389 | E52: =SUM(E48:E51) -> 49671 | F52: =SUM(F48:F51) -> 54664 | G52: =SUM(G48:G51) -> 63503 | H52: =SUM(H48:H51) -> 76559 | I52: =SUM(I48:I51) -> 86999 | J52: =SUM(J48:J51) -> 91041 | ... Q52: =SUM(Q48:Q51) -> 146878.84
B54: Current Assets
B55: ='Data Sheet'!A67 -> Receivables | C55: ='Data Sheet'!B67 -> 12322 | D55: ='Data Sheet'!C67 -> 13142 | E55: ='Data Sheet'!D67 -> 14827 | F55: ='Data Sheet'!E67 -> 18487 | G55: ='Data Sheet'!F67 -> 19294 | H55: ='Data Sheet'!G67 -> 22698 | I55: ='Data Sheet'!H67 -> 25424 | ... L55: ='Data Sheet'!K67 -> 35234 | M55: =Calculation!M58 -> 37083.325 | N55: =Calculation!N58 -> 41002.689 | O55: =Calculation!O58 -> 45202.889 | P55: =Calculation!P58 -> 50025.206 | Q55: =Calculation!Q58 -> 54689.824
B56: ='Data Sheet'!A68 -> Inventory | C56: ='Data Sheet'!B68 -> 0 | D56: ='Data Sheet'!C68 -> 0 | E56: ='Data Sheet'!D68 -> 0 | F56: ='Data Sheet'!E68 -> 0 | G56: ='Data Sheet'!F68 -> 0 | H56: ='Data Sheet'!G68 -> 0 | I56: ='Data Sheet'!H68 -> 0 | ... L56: ='Data Sheet'!K68 -> 0 | M56: =L56 -> 0 | N56: =M56 -> 0 | O56: =N56 -> 0 | P56: =O56 -> 0 | Q56: =P56 -> 0
B57: ='Data Sheet'!A69 -> Cash & Bank | C57: ='Data Sheet'!B69 -> 22625 | D57: ='Data Sheet'!C69 -> 19818 | E57: ='Data Sheet'!D69 -> 19568 | F57: ='Data Sheet'!E69 -> 18649 | G57: ='Data Sheet'!F69 -> 24714 | H57: ='Data Sheet'!G69 -> 17472 | I57: ='Data Sheet'!H69 -> 12173 | ... L57: ='Data Sheet'!K69 -> 22201 | M57: =M95 -> 16369.381 | N57: =N95 -> 28431.463 | O57: =O95 -> 40851.711 | P57: =P95 -> 53630.435 | Q57: =Q95 -> 66333.624
B58: Total Current Assets | C58: =SUM(C55:C57) -> 34947 | D58: =SUM(D55:D57) -> 32960 | E58: =SUM(E55:E57) -> 34395 | F58: =SUM(F55:F57) -> 37136 | G58: =SUM(G55:G57) -> 44008 | H58: =SUM(H55:H57) -> 40170 | I58: =SUM(I55:I57) -> 37597 | J58: =SUM(J55:J57) -> 44979 | ... Q58: =SUM(Q55:Q57) -> 121023.45
B60: Total Assets | C60: =SUM(C58,C52) -> 83148 | D60: =SUM(D58,D52) -> 79349 | E60: =SUM(E58,E52) -> 84066 | F60: =SUM(F58,F52) -> 91800 | G60: =SUM(G58,G52) -> 107511 | H60: =SUM(H58,H52) -> 116729 | I60: =SUM(I58,I52) -> 124596 | J60: =SUM(J58,J52) -> 136020 | ... Q60: =SUM(Q58,Q52) -> 267902.29
M61: =IF(M60=M45,"OK","ERROR") -> OK | N61: =IF(N60=N45,"OK","ERROR") -> OK | O61: =IF(O60=O45,"OK","ERROR") -> OK | P61: =IF(P60=P45,"OK","ERROR") -> OK | Q61: =IF(Q60=Q45,"OK","ERROR") -> OK
A63: * | B63: ="Cash-Flow Statement for "&'Data Sheet'!B1 -> Cash-Flow Statement for INFOSYS LTD
B64: ='Manual Data'!B3 -> Cash from Operating Activity
B65: ='Manual Data'!B4 -> Profit from operations | C65: ='Manual Data'!C4 -> 19340 | D65: ='Manual Data'!D4 -> 19963 | E65: ='Manual Data'!E4 -> 22126 | F65: ='Manual Data'!F4 -> 23920 | G65: ='Manual Data'!G4 -> 28845 | H65: ='Manual Data'!H4 -> 32921 | I65: ='Manual Data'!I4 -> 37605 | ... L65: ='Manual Data'!L4 -> 45273 | M65: =M14+M13-M17 -> 49239.44 | N65: =N14+N13-N17 -> 53764.943 | O65: =O14+O13-O17 -> 58768.704 | P65: =P14+P13-P17 -> 64791.39 | Q65: =Q14+Q13-Q17 -> 71439.535
B66: ='Manual Data'!B5 -> Receivables | C66: ='Manual Data'!C5 -> -1743 | D66: ='Manual Data'!D5 -> -1523 | E66: ='Manual Data'!E5 -> -2881 | F66: ='Manual Data'!F5 -> -3861 | G66: ='Manual Data'!G5 -> -1835 | H66: ='Manual Data'!H5 -> -7937 | I66: ='Manual Data'!I5 -> -7076 | ... L66: ='Manual Data'!L5 -> -5177 | M66: =IF(M55>L55,-ABS(M55-L55),ABS(M55-L55)) -> -1849.3253 | N66: =IF(N55>M55,-ABS(N55-M55),ABS(N55-M55)) -> -3919.3635 | O66: =IF(O55>N55,-ABS(O55-N55),ABS(O55-N55)) -> -4200.2003 | P66: =IF(P55>O55,-ABS(P55-O55),ABS(P55-O55)) -> -4822.3164 | Q66: =IF(Q55>P55,-ABS(Q55-P55),ABS(Q55-P55)) -> -4664.6185
B67: ='Manual Data'!B6 -> Payables | C67: ='Manual Data'!C6 -> -19 | D67: ='Manual Data'!D6 -> 328 | E67: ='Manual Data'!E6 -> 916 | F67: ='Manual Data'!F6 -> -373 | G67: ='Manual Data'!G6 -> -245 | H67: ='Manual Data'!H6 -> 1489 | I67: ='Manual Data'!I6 -> -279 | ... L67: ='Manual Data'!L6 -> -26 | M67: =IF(M39>L39,ABS(M39-L39),-ABS(M39-L39)) -> -237.92681 | N67: =IF(N39>M39,ABS(N39-M39),-ABS(N39-M39)) -> 856.83093 | O67: =IF(O39>N39,ABS(O39-N39),-ABS(O39-N39)) -> 915.52262 | P67: =IF(P39>O39,ABS(P39-O39),-ABS(P39-O39)) -> 804.34236 | Q67: =IF(Q39>P39,ABS(Q39-P39),-ABS(Q39-P39)) -> 582.18398
B68: ='Manual Data'!B7 -> Loans Advances | C68: ='Manual Data'!C7 -> 0 | D68: ='Manual Data'!D7 -> 0 | E68: ='Manual Data'!E7 -> 0 | F68: ='Manual Data'!F7 -> 0 | G68: ='Manual Data'!G7 -> -534 | H68: ='Manual Data'!H7 -> -1914 | I68: ='Manual Data'!I7 -> -3108 | ... L68: ='Manual Data'!L7 -> -2645 | M68: =IF(M51>L51,-ABS(M51-L51),ABS(M51-L51)) -> -7489.3229 | N68: =IF(N51>M51,-ABS(N51-M51),ABS(N51-M51)) -> -5018.2556 | O68: =IF(O51>N51,-ABS(O51-N51),ABS(O51-N51)) -> -4434.976 | P68: =IF(P51>O51,-ABS(P51-O51),ABS(P51-O51)) -> -5382.0376 | Q68: =IF(Q51>P51,-ABS(Q51-P51),ABS(Q51-P51)) -> -6559.0006
B69: ='Manual Data'!B8 -> Other WC items | C69: ='Manual Data'!C8 -> -394 | D69: ='Manual Data'!D8 -> 1279 | E69: ='Manual Data'!E8 -> 1512 | F69: ='Manual Data'!F8 -> 1867 | G69: ='Manual Data'!G8 -> 3382 | H69: ='Manual Data'!H8 -> 6938 | I69: ='Manual Data'!I8 -> 4119 | ... L69: ='Manual Data'!L8 -> 5209 | M69: =IF(M35>L35,ABS(M35-L35),-ABS(M35-L35)) -> -2293.0528 | N69: =IF(N35>M35,ABS(N35-M35),-ABS(N35-M35)) -> 5167.5836 | O69: =IF(O35>N35,ABS(O35-N35),-ABS(O35-N35)) -> 5978.8782 | P69: =IF(P35>O35,ABS(P35-O35),-ABS(P35-O35)) -> 6339.1533 | Q69: =IF(Q35>P35,ABS(Q35-P35),-ABS(Q35-P35)) -> 7216.7825
B70: ='Manual Data'!B9 -> Working capital changes | C70: ='Manual Data'!C9 -> -2156 | D70: ='Manual Data'!D9 -> 84 | E70: ='Manual Data'!E9 -> -453 | F70: ='Manual Data'!F9 -> -2367 | G70: ='Manual Data'!G9 -> 768 | H70: ='Manual Data'!H9 -> -1424 | I70: ='Manual Data'!I9 -> -6344 | ... L70: ='Manual Data'!L9 -> -2639 | M70: =SUM(M66:M69) -> -11869.628 | N70: =SUM(N66:N69) -> -2913.2046 | O70: =SUM(O66:O69) -> -1740.7754 | P70: =SUM(P66:P69) -> -3060.8584 | Q70: =SUM(Q66:Q69) -> -3424.6527
B71: ='Manual Data'!B10 -> Direct taxes | C71: ='Manual Data'!C10 -> -5653 | D71: ='Manual Data'!D10 -> -6829 | E71: ='Manual Data'!E10 -> -6832 | F71: ='Manual Data'!F10 -> -4550 | G71: ='Manual Data'!G10 -> -6389 | H71: ='Manual Data'!H10 -> -7612 | I71: ='Manual Data'!I10 -> -8794 | ... L71: ='Manual Data'!L10 -> -8648 | M71: =-M22 -> -13217.314 | N71: =-N22 -> -14361.073 | O71: =-O22 -> -16024.434 | P71: =-P22 -> -17699.555 | Q71: =-Q22 -> -19725.456
B72: ='Manual Data'!B11 -> Cash-Flow from Operating Activity | C72: ='Manual Data'!C11 -> 11531 | D72: ='Manual Data'!D11 -> 13218 | E72: ='Manual Data'!E11 -> 14841 | F72: ='Manual Data'!F11 -> 17003 | G72: ='Manual Data'!G11 -> 23224 | H72: ='Manual Data'!H11 -> 23885 | I72: ='Manual Data'!I11 -> 22467 | ... L72: ='Manual Data'!L11 -> 33986 | M72: =SUM(M65,M70,M71) -> 24152.498 | N72: =SUM(N65,N70,N71) -> 36490.665 | O72: =SUM(O65,O70,O71) -> 41003.495 | P72: =SUM(P65,P70,P71) -> 44030.977 | Q72: =SUM(Q65,Q70,Q71) -> 48289.426
B74: ='Manual Data'!B13 -> Cash from Investing Activity
B75: ='Manual Data'!B14 -> Fixed assets purchased | C75: ='Manual Data'!C14 -> -2760 | D75: ='Manual Data'!D14 -> -1998 | E75: ='Manual Data'!E14 -> -2445 | F75: ='Manual Data'!F14 -> -3307 | G75: ='Manual Data'!G14 -> -2107 | H75: ='Manual Data'!H14 -> -2161 | I75: ='Manual Data'!I14 -> -2579 | ... L75: ='Manual Data'!L14 -> -2727 | M75: =-Calculation!S6 -> -4606.0312 | N75: =-Calculation!T6 -> -4704.311 | O75: =-Calculation!U6 -> -5020.6413 | P75: =-Calculation!V6 -> -5303.1497 | Q75: =-Calculation!W6 -> -5369.4902
B76: ='Manual Data'!B15 -> Investments purchased | C76: ='Manual Data'!C15 -> -66410 | D76: ='Manual Data'!D15 -> -69159 | E76: ='Manual Data'!E15 -> -79410 | F76: ='Manual Data'!F15 -> -37482 | G76: ='Manual Data'!G15 -> -46738 | H76: ='Manual Data'!H15 -> -59951 | I76: ='Manual Data'!I15 -> -75800 | ... L76: ='Manual Data'!L15 -> -82617 | M76: =IF(M50>L50,-ABS(M50-L50),ABS(M50-L50)) -> -7882.3783 | N76: =IF(N50>M50,-ABS(N50-M50),ABS(N50-M50)) -> -1080.9457 | O76: =IF(O50>N50,-ABS(O50-N50),ABS(O50-N50)) -> -2390.3548 | P76: =IF(P50>O50,-ABS(P50-O50),ABS(P50-O50)) -> -3431.2598 | Q76: =IF(Q50>P50,-ABS(Q50-P50),ABS(Q50-P50)) -> -4930.8674
B77: ='Manual Data'!B16 -> Investments sold | C77: ='Manual Data'!C16 -> 52048 | D77: ='Manual Data'!D16 -> 74003 | E77: ='Manual Data'!E16 -> 78098 | F77: ='Manual Data'!F16 -> 38861 | G77: ='Manual Data'!G16 -> 40381 | H77: ='Manual Data'!H16 -> 57356 | I77: ='Manual Data'!I16 -> 76722 | ... L77: ='Manual Data'!L16 -> 89699 | N77: 0 | O77: 0 | P77: 0 | Q77: 0
B78: ='Manual Data'!B17 -> Interest received | C78: ='Manual Data'!C17 -> 0 | D78: ='Manual Data'!D17 -> 0 | E78: ='Manual Data'!E17 -> 0 | F78: ='Manual Data'!F17 -> 0 | G78: ='Manual Data'!G17 -> 0 | H78: ='Manual Data'!H17 -> 0 | I78: ='Manual Data'!I17 -> 0 | ... L78: ='Manual Data'!L17 -> 0 | M78: =L78 -> 0 | N78: =M78 -> 0 | O78: =N78 -> 0 | P78: =O78 -> 0 | Q78: =P78 -> 0
B79: ='Manual Data'!B18 -> Dividends received | C79: ='Manual Data'!C18 -> 2753 | D79: ='Manual Data'!D18 -> 1768 | E79: ='Manual Data'!E18 -> 1557 | F79: ='Manual Data'!F18 -> 1929 | G79: ='Manual Data'!G18 -> 1418 | H79: ='Manual Data'!H18 -> 1898 | I79: ='Manual Data'!I18 -> 1525 | ... L79: ='Manual Data'!L18 -> 2713 | M79: =M18 -> 5625.8377 | N79: =N18 -> 5847.3417 | O79: =O18 -> 5961.0275 | P79: =P18 -> 6303.0967 | Q79: =Q18 -> 6740.2952
B80: ='Manual Data'!B19 -> Acquisition of companies | C80: ='Manual Data'!C19 -> 0 | D80: ='Manual Data'!D19 -> 0 | E80: ='Manual Data'!E19 -> 0 | F80: ='Manual Data'!F19 -> 0 | G80: ='Manual Data'!G19 -> 0 | H80: ='Manual Data'!H19 -> 0 | I80: ='Manual Data'!I19 -> 0 | ... L80: ='Manual Data'!L19 -> 0 | M80: =L80 -> 0 | N80: =M80 -> 0 | O80: =N80 -> 0 | P80: =O80 -> 0 | Q80: =P80 -> 0
B81: ='Manual Data'!B20 -> Inter corporate deposits | C81: ='Manual Data'!C20 -> -164 | D81: ='Manual Data'!D20 -> -130 | E81: ='Manual Data'!E20 -> -24 | F81: ='Manual Data'!F20 -> -108 | G81: ='Manual Data'!G20 -> 0 | H81: ='Manual Data'!H20 -> 0 | I81: ='Manual Data'!I20 -> 0 | ... L81: ='Manual Data'!L20 -> 0 | M81: =L81 -> 0 | N81: =M81 -> 0 | O81: =N81 -> 0 | P81: =O81 -> 0 | Q81: =P81 -> 0
B82: ='Manual Data'!B21 -> Other investing items | C82: ='Manual Data'!C21 -> -131 | D82: ='Manual Data'!D21 -> 49 | E82: ='Manual Data'!E21 -> 1592 | F82: ='Manual Data'!F21 -> -224 | G82: ='Manual Data'!G21 -> -327 | H82: ='Manual Data'!H21 -> -3627 | I82: ='Manual Data'!I21 -> -939 | ... L82: ='Manual Data'!L21 -> -3522 | M82: =IF(M49>L49,-ABS(M49-L49),ABS(M49-L49)) -> -1046.295 | N82: =IF(N49>M49,-ABS(N49-M49),ABS(N49-M49)) -> 169.33563 | O82: =IF(O49>N49,-ABS(O49-N49),ABS(O49-N49)) -> 279.41062 | P82: =IF(P49>O49,-ABS(P49-O49),ABS(P49-O49)) -> 173.56113 | Q82: =IF(Q49>P49,-ABS(Q49-P49),ABS(Q49-P49)) -> 31.719116
B83: ='Manual Data'!B22 -> Cash-Flow from Investing Activity | C83: ='Manual Data'!C22 -> -14664 | D83: ='Manual Data'!D22 -> 4533 | E83: ='Manual Data'!E22 -> -632 | F83: ='Manual Data'!F22 -> -331 | G83: ='Manual Data'!G22 -> -7373 | H83: ='Manual Data'!H22 -> -6485 | I83: ='Manual Data'!I22 -> -1071 | ... L83: ='Manual Data'!L22 -> 3546 | M83: =SUM(M75:M82) -> -7908.8668 | N83: =SUM(N75:N82) -> 231.42056 | O83: =SUM(O75:O82) -> -1170.5579 | P83: =SUM(P75:P82) -> -2257.7516 | Q83: =SUM(Q75:Q82) -> -3528.3432
B85: ='Manual Data'!B24 -> Cash from Financing Activity
B86: ='Manual Data'!B25 -> Proceeds from shares | C86: ='Manual Data'!C25 -> 0 | D86: ='Manual Data'!D25 -> 5 | E86: ='Manual Data'!E25 -> 6 | F86: ='Manual Data'!F25 -> 6 | G86: ='Manual Data'!G25 -> 15 | H86: ='Manual Data'!H25 -> 21 | I86: ='Manual Data'!I25 -> 35 | ... L86: ='Manual Data'!L25 -> 2 | M86: 0 | N86: 0 | O86: 0 | P86: 0 | Q86: 0
B87: ='Manual Data'!B26 -> Repayment of borrowings | C87: ='Manual Data'!C26 -> 0 | D87: ='Manual Data'!D26 -> 0 | E87: ='Manual Data'!E26 -> 0 | F87: ='Manual Data'!F26 -> 0 | G87: ='Manual Data'!G26 -> 0 | H87: ='Manual Data'!H26 -> 0 | I87: ='Manual Data'!I26 -> 0 | ... L87: ='Manual Data'!L26 -> 0 | M87: =L87 -> 0 | N87: =M87 -> 0 | O87: =N87 -> 0 | P87: =O87 -> 0 | Q87: =P87 -> 0
B88: ='Manual Data'!B27 -> Dividends paid | C88: ='Manual Data'!C27 -> -6939 | D88: ='Manual Data'!D27 -> -7464 | E88: ='Manual Data'!E27 -> -13705 | F88: ='Manual Data'!F27 -> -9548 | G88: ='Manual Data'!G27 -> -9137 | H88: ='Manual Data'!H27 -> -12731 | I88: ='Manual Data'!I27 -> -13653 | ... L88: ='Manual Data'!L27 -> -18656 | M88: =-Calculation!M45 -> -22075.25 | N88: =-Calculation!N45 -> -24660.004 | O88: =-Calculation!O45 -> -27412.689 | P88: =-Calculation!P45 -> -28994.5 | Q88: =-Calculation!Q45 -> -32057.894
B89: ='Manual Data'!B28 -> Financial liabilities | C89: ='Manual Data'!C28 -> 0 | D89: ='Manual Data'!D28 -> 0 | E89: ='Manual Data'!E28 -> 0 | F89: ='Manual Data'!F28 -> -571 | G89: ='Manual Data'!G28 -> -698 | H89: ='Manual Data'!H28 -> -915 | I89: ='Manual Data'!I28 -> -1231 | ... L89: ='Manual Data'!L28 -> -2824 | M89: 0 | N89: 0 | O89: 0 | P89: 0 | Q89: 0
B90: ='Manual Data'!B29 -> Other financing items | C90: ='Manual Data'!C29 -> 0 | D90: ='Manual Data'!D29 -> -13046 | E90: ='Manual Data'!E29 -> -813 | F90: ='Manual Data'!F29 -> -7478 | G90: ='Manual Data'!G29 -> 34 | H90: ='Manual Data'!H29 -> -11017 | I90: ='Manual Data'!I29 -> -11846 | ... L90: ='Manual Data'!L29 -> -18308 | M90: 0 | N90: 0 | O90: 0 | P90: 0 | Q90: 0
B91: ='Manual Data'!B30 -> Cash-Flow from Financing Activity | C91: ='Manual Data'!C30 -> -6939 | D91: ='Manual Data'!D30 -> -20505 | E91: ='Manual Data'!E30 -> -14512 | F91: ='Manual Data'!F30 -> -17591 | G91: ='Manual Data'!G30 -> -9786 | H91: ='Manual Data'!H30 -> -24642 | I91: ='Manual Data'!I30 -> -26695 | ... L91: ='Manual Data'!L30 -> -39786 | M91: =SUM(M86:M90) -> -22075.25 | N91: =SUM(N86:N90) -> -24660.004 | O91: =SUM(O86:O90) -> -27412.689 | P91: =SUM(P86:P90) -> -28994.5 | Q91: =SUM(Q86:Q90) -> -32057.894
B93: Opening Balance | C93: 32697 | D93: =C95 -> 22625 | E93: =D95 -> 19871 | F93: =E95 -> 19568 | G93: =F95 -> 18649 | H93: =G95 -> 24714 | I93: =H95 -> 17472 | J93: =I95 -> 12173 | K93: =J95 -> 14786 | ... Q93: =P95 -> 53630.435
B94: ='Manual Data'!B32 -> Net Cash Flow | C94: ='Manual Data'!C32 -> -10072 | D94: ='Manual Data'!D32 -> -2754 | E94: ='Manual Data'!E32 -> -303 | F94: ='Manual Data'!F32 -> -919 | G94: ='Manual Data'!G32 -> 6065 | H94: ='Manual Data'!H32 -> -7242 | I94: ='Manual Data'!I32 -> -5299 | ... L94: ='Manual Data'!L32 -> -2254 | M94: =SUM(M91,M83,M72) -> -5831.619 | N94: =SUM(N91,N83,N72) -> 12062.082 | O94: =SUM(O91,O83,O72) -> 12420.248 | P94: =SUM(P91,P83,P72) -> 12778.725 | Q94: =SUM(Q91,Q83,Q72) -> 12703.189
B95: Closing Balance | C95: =SUM(C93:C94) -> 22625 | D95: =SUM(D93:D94) -> 19871 | E95: =SUM(E93:E94) -> 19568 | F95: =SUM(F93:F94) -> 18649 | G95: =SUM(G93:G94) -> 24714 | H95: =SUM(H93:H94) -> 17472 | I95: =SUM(I93:I94) -> 12173 | J95: =SUM(J93:J94) -> 14786 | ... Q95: =SUM(Q93:Q94) -> 66333.624

Sheet Ratios Analysis
B1: ="Ratios Analysis for "&'Data Sheet'!B1 -> Ratios Analysis for INFOSYS LTD
B2: ='Data Sheet'!A16 -> Report Date | C2: ='Data Sheet'!B16 -> 42825 | D2: ='Data Sheet'!C16 -> 43190 | E2: ='Data Sheet'!D16 -> 43555 | F2: ='Data Sheet'!E16 -> 43921 | G2: ='Data Sheet'!F16 -> 44286 | H2: ='Data Sheet'!G16 -> 44651 | I2: ='Data Sheet'!H16 -> 45016 | ... L2: ='Data Sheet'!K16 -> 46112 | M2: =L2+365 -> 46477 | N2: =M2+365 -> 46842 | O2: =N2+365 -> 47207 | P2: =O2+365 -> 47572 | Q2: =P2+365 -> 47937
A3: * | B3: Profitability Ratios
B4: Gross Profit Margin | C4: ='Historical Financial Statement'!C6 -> 0.34862158 | D4: ='Historical Financial Statement'!D6 -> 0.34212019 | E4: ='Historical Financial Statement'!E6 -> 0.32934986 | F4: ='Historical Financial Statement'!F6 -> 0.31479993 | G4: ='Historical Financial Statement'!G6 -> 0.31831754 | H4: ='Historical Financial Statement'!H6 -> 0.30271043 | I4: ='Historical Financial Statement'!I6 -> 0.28539794 | J4: ='Historical Financial Statement'!J6 -> 0.28398516 | ... Q4: ='Historical Financial Statement'!Q6 -> 0.29720635
B5: EBITDA Margin | C5: ='Historical Financial Statement'!C11 -> 0.27165469 | D5: ='Historical Financial Statement'!D11 -> 0.26689544 | E5: ='Historical Financial Statement'!E11 -> 0.24396734 | F5: ='Historical Financial Statement'!F11 -> 0.24525559 | G5: ='Historical Financial Statement'!G11 -> 0.27757982 | H5: ='Historical Financial Statement'!H11 -> 0.25888475 | I5: ='Historical Financial Statement'!I11 -> 0.23935898 | J5: ='Historical Financial Statement'!J11 -> 0.2370339 | ... Q5: ='Historical Financial Statement'!Q11 -> 0.24884987
B6: EBIT Margin | C6: ='Historical Financial Statement'!C15 -> 0.24678757 | D6: ='Historical Financial Statement'!D15 -> 0.24047815 | E6: ='Historical Financial Statement'!E15 -> 0.21964318 | F6: ='Historical Financial Statement'!F15 -> 0.2133912 | G6: ='Historical Financial Statement'!G15 -> 0.2450633 | H6: ='Historical Financial Statement'!H15 -> 0.23030886 | I6: ='Historical Financial Statement'!I15 -> 0.21057186 | J6: ='Historical Financial Statement'!J15 -> 0.20659205 | ... Q6: ='Historical Financial Statement'!Q15 -> 0.23170676
B7: Net Profit Margin | C7: ='Historical Financial Statement'!C24 -> 0.2095818 | D7: ='Historical Financial Statement'!D24 -> 0.22729077 | E7: ='Historical Financial Statement'!E24 -> 0.1863925 | F7: ='Historical Financial Statement'!F24 -> 0.18326706 | G7: ='Historical Financial Statement'!G24 -> 0.19331754 | H7: ='Historical Financial Statement'!H24 -> 0.18206033 | I7: ='Historical Financial Statement'!I24 -> 0.16426036 | J7: ='Historical Financial Statement'!J24 -> 0.17080757 | ... Q7: ='Historical Financial Statement'!Q24 -> 0.18544177
B8: Return on Equity | C8: ='Historical Financial Statement'!C23/SUM('Historical Financial Statement'!C29:C30) -> 0.20806877 | D8: ='Historical Financial Statement'!D23/SUM('Historical Financial Statement'!D29:D30) -> 0.24689247 | E8: ='Historical Financial Statement'!E23/SUM('Historical Financial Statement'!E29:E30) -> 0.23726674 | F8: ='Historical Financial Statement'!F23/SUM('Historical Financial Statement'!F29:F30) -> 0.2542246 | G8: ='Historical Financial Statement'!G23/SUM('Historical Financial Statement'!G29:G30) -> 0.25439091 | H8: ='Historical Financial Statement'!H23/SUM('Historical Financial Statement'!H29:H30) -> 0.29390843 | I8: ='Historical Financial Statement'!I23/SUM('Historical Financial Statement'!I29:I30) -> 0.31970507 | J8: ='Historical Financial Statement'!J23/SUM('Historical Financial Statement'!J29:J30) -> 0.29788007 | ... Q8: ='Historical Financial Statement'!Q23/SUM('Historical Financial Statement'!Q29:Q30) -> 0.29540156
B9: Return on Assets | C9: ='Historical Financial Statement'!C23/'Historical Financial Statement'!C60 -> 0.17261991 | D9: ='Historical Financial Statement'!D23/'Historical Financial Statement'!D60 -> 0.20200633 | E9: ='Historical Financial Statement'!E23/'Historical Financial Statement'!E60 -> 0.18330835 | F9: ='Historical Financial Statement'!F23/'Historical Financial Statement'!F60 -> 0.18125272 | G9: ='Historical Financial Statement'!G23/'Historical Financial Statement'!G60 -> 0.18066058 | H9: ='Historical Financial Statement'!H23/'Historical Financial Statement'!H60 -> 0.18972149 | I9: ='Historical Financial Statement'!I23/'Historical Financial Statement'!I60 -> 0.19348936 | J9: ='Historical Financial Statement'!J23/'Historical Financial Statement'!J60 -> 0.19297162 | ... Q9: ='Historical Financial Statement'!Q23/'Historical Financial Statement'!Q60 -> 0.19972899
B10: Return on Capital Employed | C10: ='Historical Financial Statement'!C14/SUM('Historical Financial Statement'!C29:C30,'Historical Financial Statement'!C34) -> 0.24500594 | D10: ='Historical Financial Statement'!D14/SUM('Historical Financial Statement'!D29:D30,'Historical Financial Statement'!D34) -> 0.26121713 | E10: ='Historical Financial Statement'!E14/SUM('Historical Financial Statement'!E29:E30,'Historical Financial Statement'!E34) -> 0.27959291 | F10: ='Historical Financial Statement'!F14/SUM('Historical Financial Statement'!F29:F30,'Historical Financial Statement'!F34) -> 0.27644365 | G10: ='Historical Financial Statement'!G14/SUM('Historical Financial Statement'!G29:G30,'Historical Financial Statement'!G34) -> 0.30145943 | H10: ='Historical Financial Statement'!H14/SUM('Historical Financial Statement'!H29:H30,'Historical Financial Statement'!H34) -> 0.34661734 | I10: ='Historical Financial Statement'!I14/SUM('Historical Financial Statement'!I29:I30,'Historical Financial Statement'!I34) -> 0.3692089 | J10: ='Historical Financial Statement'!J14/SUM('Historical Financial Statement'!J29:J30,'Historical Financial Statement'!J34) -> 0.32906971 | ... Q10: ='Historical Financial Statement'!Q14/SUM('Historical Financial Statement'!Q29:Q30,'Historical Financial Statement'!Q34) -> 0.35130353
B11: Reuturn on Invested Capital Employed | C11: ='Historical Financial Statement'!C23/SUM('Historical Financial Statement'!C31,'Historical Financial Statement'!C34) -> 0.20806877 | D11: ='Historical Financial Statement'!D23/SUM('Historical Financial Statement'!D31,'Historical Financial Statement'!D34) -> 0.24689247 | E11: ='Historical Financial Statement'!E23/SUM('Historical Financial Statement'!E31,'Historical Financial Statement'!E34) -> 0.23726674 | F11: ='Historical Financial Statement'!F23/SUM('Historical Financial Statement'!F31,'Historical Financial Statement'!F34) -> 0.23741849 | G11: ='Historical Financial Statement'!G23/SUM('Historical Financial Statement'!G31,'Historical Financial Statement'!G34) -> 0.23780548 | H11: ='Historical Financial Statement'!H23/SUM('Historical Financial Statement'!H31,'Historical Financial Statement'!H34) -> 0.27400277 | I11: ='Historical Financial Statement'!I23/SUM('Historical Financial Statement'!I31,'Historical Financial Statement'!I34) -> 0.28800803 | J11: ='Historical Financial Statement'!J23/SUM('Historical Financial Statement'!J31,'Historical Financial Statement'!J34) -> 0.27207048 | ... Q11: ='Historical Financial Statement'!Q23/SUM('Historical Financial Statement'!Q31,'Historical Financial Statement'!Q34) -> 0.2811586
A13: * | B13: Solvency Ratios
B14: D/E Ratio | C14: ='Historical Financial Statement'!C34/SUM('Historical Financial Statement'!C29:C30) -> 0 | D14: ='Historical Financial Statement'!D34/SUM('Historical Financial Statement'!D29:D30) -> 0 | E14: ='Historical Financial Statement'!E34/SUM('Historical Financial Statement'!E29:E30) -> 0 | F14: ='Historical Financial Statement'!F34/SUM('Historical Financial Statement'!F29:F30) -> 0.07078686 | G14: ='Historical Financial Statement'!G34/SUM('Historical Financial Statement'!G29:G30) -> 0.069743684 | H14: ='Historical Financial Statement'!H34/SUM('Historical Financial Statement'!H29:H30) -> 0.072647644 | I14: ='Historical Financial Statement'!I34/SUM('Historical Financial Statement'!I29:I30) -> 0.1100561 | J14: ='Historical Financial Statement'!J34/SUM('Historical Financial Statement'!J29:J30) -> 0.094863589 | ... Q14: ='Historical Financial Statement'!Q34/SUM('Historical Financial Statement'!Q29:Q30) -> 0.050658071
B15: Debt Ratio | C15: ='Historical Financial Statement'!C34/'Historical Financial Statement'!C60 -> 0 | D15: ='Historical Financial Statement'!D34/'Historical Financial Statement'!D60 -> 0 | E15: ='Historical Financial Statement'!E34/'Historical Financial Statement'!E60 -> 0 | F15: ='Historical Financial Statement'!F34/'Historical Financial Statement'!F60 -> 0.05046841 | G15: ='Historical Financial Statement'!G34/'Historical Financial Statement'!G60 -> 0.049529816 | H15: ='Historical Financial Statement'!H34/'Historical Financial Statement'!H60 -> 0.046894945 | I15: ='Historical Financial Statement'!I34/'Historical Financial Statement'!I60 -> 0.066607275 | J15: ='Historical Financial Statement'!J34/'Historical Financial Statement'!J60 -> 0.061454198 | ... Q15: ='Historical Financial Statement'!Q34/'Historical Financial Statement'!Q60 -> 0.034251293
B16: Interest Coverage Ratio | C16: =IFERROR('Historical Financial Statement'!C19/'Historical Financial Statement'!C17,0) -> 0 | D16: =IFERROR('Historical Financial Statement'!D19/'Historical Financial Statement'!D17,0) -> 0 | E16: =IFERROR('Historical Financial Statement'!E19/'Historical Financial Statement'!E17,0) -> 0 | F16: =IFERROR('Historical Financial Statement'!F19/'Historical Financial Statement'!F17,0) -> 129.45294 | G16: =IFERROR('Historical Financial Statement'!G19/'Historical Financial Statement'!G17,0) -> 136.55385 | H16: =IFERROR('Historical Financial Statement'!H19/'Historical Financial Statement'!H17,0) -> 150.55 | I16: =IFERROR('Historical Financial Statement'!I19/'Historical Financial Statement'!I17,0) -> 117.33099 | J16: =IFERROR('Historical Financial Statement'!J19/'Historical Financial Statement'!J17,0) -> 76.570213 | ... Q16: =IFERROR('Historical Financial Statement'!Q19/'Historical Financial Statement'!Q17,0) -> 201.04685
A18: * | B18: Efficency Ratios
B19: Assets Turnover Ratio | C19: ='Historical Financial Statement'!C3/'Historical Financial Statement'!C60 -> 0.82363977 | D19: ='Historical Financial Statement'!D3/'Historical Financial Statement'!D60 -> 0.88875726 | E19: ='Historical Financial Statement'!E3/'Historical Financial Statement'!E60 -> 0.98345348 | F19: ='Historical Financial Statement'!F3/'Historical Financial Statement'!F60 -> 0.98900871 | G19: ='Historical Financial Statement'!G3/'Historical Financial Statement'!G60 -> 0.93452763 | H19: ='Historical Financial Statement'!H3/'Historical Financial Statement'!H60 -> 1.0420804 | I19: ='Historical Financial Statement'!I3/'Historical Financial Statement'!I60 -> 1.1779431 | J19: ='Historical Financial Statement'!J3/'Historical Financial Statement'!J60 -> 1.1297603 | ... Q19: ='Historical Financial Statement'!Q3/'Historical Financial Statement'!Q60 -> 1.0770442
B20: Fixed Assets Turnover Ratio | C20: ='Historical Financial Statement'!C3/'Historical Financial Statement'!C48 -> 4.8299598 | D20: ='Historical Financial Statement'!D3/'Historical Financial Statement'!D48 -> 5.6085573 | E20: ='Historical Financial Statement'!E3/'Historical Financial Statement'!E48 -> 5.2625716 | F20: ='Historical Financial Statement'!F3/'Historical Financial Statement'!F48 -> 3.8165118 | G20: ='Historical Financial Statement'!G3/'Historical Financial Statement'!G48 -> 3.939306 | H20: ='Historical Financial Statement'!H3/'Historical Financial Statement'!H48 -> 4.7147674 | I20: ='Historical Financial Statement'!I3/'Historical Financial Statement'!I48 -> 5.0219675 | J20: ='Historical Financial Statement'!J3/'Historical Financial Statement'!J48 -> 5.5633191 | ... Q20: ='Historical Financial Statement'!Q3/'Historical Financial Statement'!Q48 -> 8.2904598
B21: Inventory Turnover Ratio | C21: =IFERROR('Historical Financial Statement'!C4/'Historical Financial Statement'!C56,0) -> 0 | D21: =IFERROR('Historical Financial Statement'!D4/'Historical Financial Statement'!D56,0) -> 0 | E21: =IFERROR('Historical Financial Statement'!E4/'Historical Financial Statement'!E56,0) -> 0 | F21: =IFERROR('Historical Financial Statement'!F4/'Historical Financial Statement'!F56,0) -> 0 | G21: =IFERROR('Historical Financial Statement'!G4/'Historical Financial Statement'!G56,0) -> 0 | H21: =IFERROR('Historical Financial Statement'!H4/'Historical Financial Statement'!H56,0) -> 0 | I21: =IFERROR('Historical Financial Statement'!I4/'Historical Financial Statement'!I56,0) -> 0 | J21: =IFERROR('Historical Financial Statement'!J4/'Historical Financial Statement'!J56,0) -> 0 | ... Q21: =IFERROR('Historical Financial Statement'!Q4/'Historical Financial Statement'!Q56,0) -> 0
B22: Trade Payable Turnover Ratio | C22: ='Historical Financial Statement'!C4/'Historical Financial Statement'!C39 -> 121.55041 | D22: ='Historical Financial Statement'!D4/'Historical Financial Statement'!D39 -> 66.851585 | E22: ='Historical Financial Statement'!E4/'Historical Financial Statement'!E39 -> 33.502115 | F22: ='Historical Financial Statement'!F4/'Historical Financial Statement'!F39 -> 21.812763 | G22: ='Historical Financial Statement'!G4/'Historical Financial Statement'!G39 -> 25.89414 | H22: ='Historical Financial Statement'!H4/'Historical Financial Statement'!H39 -> 20.517417 | I22: ='Historical Financial Statement'!I4/'Historical Financial Statement'!I39 -> 27.135834 | J22: ='Historical Financial Statement'!J4/'Historical Financial Statement'!J39 -> 27.813448 | ... Q22: ='Historical Financial Statement'!Q4/'Historical Financial Statement'!Q39 -> 26.456251
B23: Trade Receivable Turnover Ratio | C23: ='Historical Financial Statement'!C3/'Historical Financial Statement'!C55 -> 5.557864 | D23: ='Historical Financial Statement'!D3/'Historical Financial Statement'!D55 -> 5.3661543 | E23: ='Historical Financial Statement'!E3/'Historical Financial Statement'!E55 -> 5.5759763 | F23: ='Historical Financial Statement'!F3/'Historical Financial Statement'!F55 -> 4.9110726 | G23: ='Historical Financial Statement'!G3/'Historical Financial Statement'!G55 -> 5.207422 | H23: ='Historical Financial Statement'!H3/'Historical Financial Statement'!H55 -> 5.3591065 | I23: ='Historical Financial Statement'!I3/'Historical Financial Statement'!I55 -> 5.7727738 | J23: ='Historical Financial Statement'!J3/'Historical Financial Statement'!J55 -> 5.0895903 | ... Q23: ='Historical Financial Statement'!Q3/'Historical Financial Statement'!Q55 -> 5.2759837
A25: * | B25: Liquidity Ratios
B26: Current Ratio | C26: ='Historical Financial Statement'!C58/'Historical Financial Statement'!C41 -> 95.223433 | D26: ='Historical Financial Statement'!D58/'Historical Financial Statement'!D41 -> 47.492795 | E26: ='Historical Financial Statement'!E58/'Historical Financial Statement'!E41 -> 20.782477 | F26: ='Historical Financial Statement'!F58/'Historical Financial Statement'!F41 -> 13.021038 | G26: ='Historical Financial Statement'!G58/'Historical Financial Statement'!G41 -> 16.638185 | H26: ='Historical Financial Statement'!H58/'Historical Financial Statement'!H41 -> 9.7169811 | I26: ='Historical Financial Statement'!I58/'Historical Financial Statement'!I41 -> 9.727555 | J26: ='Historical Financial Statement'!J58/'Historical Financial Statement'!J41 -> 11.369818 | ... Q26: ='Historical Financial Statement'!Q58/'Historical Financial Statement'!Q41 -> 15.789196
B27: Quick Ratio | C27: =(SUM('Historical Financial Statement'!C55,'Historical Financial Statement'!C57)-'Historical Financial Statement'!C56)/'Historical Financial Statement'!C41 -> 95.223433 | D27: =(SUM('Historical Financial Statement'!D55,'Historical Financial Statement'!D57)-'Historical Financial Statement'!D56)/'Historical Financial Statement'!D41 -> 47.492795 | E27: =(SUM('Historical Financial Statement'!E55,'Historical Financial Statement'!E57)-'Historical Financial Statement'!E56)/'Historical Financial Statement'!E41 -> 20.782477 | F27: =(SUM('Historical Financial Statement'!F55,'Historical Financial Statement'!F57)-'Historical Financial Statement'!F56)/'Historical Financial Statement'!F41 -> 13.021038 | G27: =(SUM('Historical Financial Statement'!G55,'Historical Financial Statement'!G57)-'Historical Financial Statement'!G56)/'Historical Financial Statement'!G41 -> 16.638185 | H27: =(SUM('Historical Financial Statement'!H55,'Historical Financial Statement'!H57)-'Historical Financial Statement'!H56)/'Historical Financial Statement'!H41 -> 9.7169811 | I27: =(SUM('Historical Financial Statement'!I55,'Historical Financial Statement'!I57)-'Historical Financial Statement'!I56)/'Historical Financial Statement'!I41 -> 9.727555 | J27: =(SUM('Historical Financial Statement'!J55,'Historical Financial Statement'!J57)-'Historical Financial Statement'!J56)/'Historical Financial Statement'!J41 -> 11.369818 | ... Q27: =(SUM('Historical Financial Statement'!Q55,'Historical Financial Statement'!Q57)-'Historical Financial Statement'!Q56)/'Historical Financial Statement'!Q41 -> 15.789196
B28: Cash Ratio | C28: ='Historical Financial Statement'!C57/'Historical Financial Statement'!C41 -> 61.648501 | D28: ='Historical Financial Statement'!D57/'Historical Financial Statement'!D41 -> 28.556196 | E28: ='Historical Financial Statement'!E57/'Historical Financial Statement'!E41 -> 11.823565 | F28: ='Historical Financial Statement'!F57/'Historical Financial Statement'!F41 -> 6.5389201 | G28: ='Historical Financial Statement'!G57/'Historical Financial Statement'!G41 -> 9.3436673 | H28: ='Historical Financial Statement'!H57/'Historical Financial Statement'!H41 -> 4.2264151 | I28: ='Historical Financial Statement'!I57/'Historical Financial Statement'!I41 -> 3.1495472 | J28: ='Historical Financial Statement'!J57/'Historical Financial Statement'!J41 -> 3.7376138 | ... Q28: ='Historical Financial Statement'!Q57/'Historical Financial Statement'!Q41 -> 8.6541462
A30: * | B30: Market Ratios
B31: Eairning Per Share | C31: ='Historical Financial Statement'!C23/'Data Sheet'!B93 -> 31.243606 | D31: ='Historical Financial Statement'!D23/'Data Sheet'!C93 -> 36.694748 | E31: ='Historical Financial Statement'!E23/'Data Sheet'!D93 -> 35.272036 | F31: ='Historical Financial Statement'!F23/'Data Sheet'!E93 -> 39.067856 | G31: ='Historical Financial Statement'!G23/'Data Sheet'!F93 -> 45.586406 | H31: ='Historical Financial Statement'!H23/'Data Sheet'!G93 -> 52.644591 | I31: ='Historical Financial Statement'!I23/'Data Sheet'!H93 -> 58.11117 | J31: ='Historical Financial Statement'!J23/'Data Sheet'!I93 -> 63.234479 | ... L31: ='Historical Financial Statement'!L23/'Data Sheet'!K93 -> 72.67482 | M31: =_xlfn.FORECAST.ETS(M$2,$C31:$L31,$C$2:$L$2) -> 76.650634 | N31: =_xlfn.FORECAST.ETS(N$2,$C31:$L31,$C$2:$L$2) -> 81.30807 | O31: =_xlfn.FORECAST.ETS(O$2,$C31:$L31,$C$2:$L$2) -> 85.978232 | P31: =_xlfn.FORECAST.ETS(P$2,$C31:$L31,$C$2:$L$2) -> 90.648429 | Q31: =_xlfn.FORECAST.ETS(Q$2,$C31:$L31,$C$2:$L$2) -> 95.318626
B32: P/E Ratio | C32: ='Data Sheet'!B90/'Ratios Analysis'!C31 -> 16.359507 | D32: ='Data Sheet'!C90/'Ratios Analysis'!D31 -> 15.421825 | E32: ='Data Sheet'!D90/'Ratios Analysis'!E31 -> 21.088944 | F32: ='Data Sheet'!E90/'Ratios Analysis'!F31 -> 16.420148 | G32: ='Data Sheet'!F90/'Ratios Analysis'!G31 -> 30.010043 | H32: ='Data Sheet'!G90/'Ratios Analysis'!H31 -> 36.221195 | I32: ='Data Sheet'!H90/'Ratios Analysis'!I31 -> 24.572728 | J32: ='Data Sheet'!I90/'Ratios Analysis'!J31 -> 23.690398 | ... L32: ='Data Sheet'!K90/'Ratios Analysis'!L31 -> 17.208161 | M32: =_xlfn.FORECAST.ETS(M$2,$C32:$L32,$C$2:$L$2) -> 22.460569 | N32: =_xlfn.FORECAST.ETS(N$2,$C32:$L32,$C$2:$L$2) -> 23.148248 | O32: =_xlfn.FORECAST.ETS(O$2,$C32:$L32,$C$2:$L$2) -> 23.837806 | P32: =_xlfn.FORECAST.ETS(P$2,$C32:$L32,$C$2:$L$2) -> 24.527369 | Q32: =_xlfn.FORECAST.ETS(Q$2,$C32:$L32,$C$2:$L$2) -> 25.216932
B33: Book Value Per Share | C33: =SUM('Historical Financial Statement'!C29:C30)/'Data Sheet'!B93 -> 150.15999 | D33: =SUM('Historical Financial Statement'!D29:D30)/'Data Sheet'!C93 -> 148.62644 | E33: =SUM('Historical Financial Statement'!E29:E30)/'Data Sheet'!D93 -> 148.65985 | F33: =SUM('Historical Financial Statement'!F29:F30)/'Data Sheet'!E93 -> 153.67457 | G33: =SUM('Historical Financial Statement'!G29:G30)/'Data Sheet'!F93 -> 179.19825 | H33: =SUM('Historical Financial Statement'!H29:H30)/'Data Sheet'!G93 -> 179.11902 | I33: =SUM('Historical Financial Statement'!I29:I30)/'Data Sheet'!H93 -> 181.76493 | J33: =SUM('Historical Financial Statement'!J29:J30)/'Data Sheet'!I93 -> 212.28167 | ... L33: =SUM('Historical Financial Statement'!L29:L30)/'Data Sheet'!K93 -> 228.94763 | M33: =_xlfn.FORECAST.ETS(M$2,$C33:$L33,$C$2:$L$2) -> 241.34758 | N33: =_xlfn.FORECAST.ETS(N$2,$C33:$L33,$C$2:$L$2) -> 251.52304 | O33: =_xlfn.FORECAST.ETS(O$2,$C33:$L33,$C$2:$L$2) -> 261.72631 | P33: =_xlfn.FORECAST.ETS(P$2,$C33:$L33,$C$2:$L$2) -> 271.92966 | Q33: =_xlfn.FORECAST.ETS(Q$2,$C33:$L33,$C$2:$L$2) -> 282.13301
A35: * | B35: Operating Cycle Ratios
B36: Inventory Days | C36: =IFERROR(365/C21,0) -> 0 | D36: =IFERROR(365/D21,0) -> 0 | E36: =IFERROR(365/E21,0) -> 0 | F36: =IFERROR(365/F21,0) -> 0 | G36: =IFERROR(365/G21,0) -> 0 | H36: =IFERROR(365/H21,0) -> 0 | I36: =IFERROR(365/I21,0) -> 0 | J36: =IFERROR(365/J21,0) -> 0 | ... Q36: =IFERROR(365/Q21,0) -> 0
B37: Trade Payable Days | C37: =365/C22 -> 3.0028694 | D37: =365/D22 -> 5.4598556 | E37: =365/E22 -> 10.894835 | F37: =365/F22 -> 16.733323 | G37: =365/G22 -> 14.095853 | H37: =365/H22 -> 17.789764 | I37: =365/I22 -> 13.450849 | J37: =365/J22 -> 13.123148 | ... Q37: =365/Q22 -> 13.796362
B38: Trade Receivable Days | C38: =365/C23 -> 65.672712 | D38: =365/D23 -> 68.018916 | E38: =365/E23 -> 65.459389 | F38: =365/F23 -> 74.321849 | G38: =365/G23 -> 70.092265 | H38: =365/H23 -> 68.108368 | I38: =365/I23 -> 63.227837 | J38: =365/J23 -> 71.715006 | ... Q38: =365/Q23 -> 69.181412
B39: Cash Conversion Cycle | C39: =SUM(C36,C38)-C37 -> 62.669842 | D39: =SUM(D36,D38)-D37 -> 62.55906 | E39: =SUM(E36,E38)-E37 -> 54.564555 | F39: =SUM(F36,F38)-F37 -> 57.588526 | G39: =SUM(G36,G38)-G37 -> 55.996411 | H39: =SUM(H36,H38)-H37 -> 50.318604 | I39: =SUM(I36,I38)-I37 -> 49.776989 | J39: =SUM(J36,J38)-J37 -> 58.591858 | ... Q39: =SUM(Q36,Q38)-Q37 -> 55.38505
A41: * | B41: Market Prospect Ratios
B42: Dividend Payout Ratio | C42: ='Data Sheet'!B31/'Historical Financial Statement'!C23 -> 0.41047865 | D42: ='Data Sheet'!C31/'Historical Financial Statement'!D23 -> 0.59052966 | E42: ='Data Sheet'!D31/'Historical Financial Statement'!E23 -> 0.59847502 | F42: ='Data Sheet'!E31/'Historical Financial Statement'!F23 -> 0.44636096 | G42: ='Data Sheet'!F31/'Historical Financial Statement'!G23 -> 0.5905164 | H42: ='Data Sheet'!G31/'Historical Financial Statement'!H23 -> 0.58735663 | I42: ='Data Sheet'!H31/'Historical Financial Statement'!I23 -> 0.58359051 | J42: ='Data Sheet'!I31/'Historical Financial Statement'!J23 -> 0.7258915 | ... L42: ='Data Sheet'!K31/'Historical Financial Statement'!L23 -> 0.65923865 | M42: =_xlfn.FORECAST.ETS(M$2,$C42:$L42,$C$2:$L$2) -> 0.70855164 | N42: =_xlfn.FORECAST.ETS(N$2,$C42:$L42,$C$2:$L$2) -> 0.73187381 | O42: =_xlfn.FORECAST.ETS(O$2,$C42:$L42,$C$2:$L$2) -> 0.7552597 | P42: =_xlfn.FORECAST.ETS(P$2,$C42:$L42,$C$2:$L$2) -> 0.77864577 | Q42: =_xlfn.FORECAST.ETS(Q$2,$C42:$L42,$C$2:$L$2) -> 0.80203183
B43: Retention Ratio | C43: =1-C42 -> 0.58952135 | D43: =1-D42 -> 0.40947034 | E43: =1-E42 -> 0.40152498 | F43: =1-F42 -> 0.55363904 | G43: =1-G42 -> 0.4094836 | H43: =1-H42 -> 0.41264337 | I43: =1-I42 -> 0.41640949 | J43: =1-J42 -> 0.2741085 | ... Q43: =1-Q42 -> 0.19796817
B44: Sustainability Ratio | C44: =C43*C8 -> 0.12266098 | D44: =D43*D8 -> 0.10109514 | E44: =E43*E8 -> 0.095268523 | F44: =F43*F8 -> 0.14074866 | G44: =G43*G8 -> 0.1041689 | H44: =H43*H8 -> 0.12127936 | I44: =I43*I8 -> 0.13312822 | J44: =J43*J8 -> 0.081651459 | ... Q44: =Q43*Q8 -> 0.058480104

Sheet DuPont Model
B1: ="DuPont Models for "&'Data Sheet'!B1 -> DuPont Models for INFOSYS LTD
B2: ='Data Sheet'!A16 -> Report Date | C2: ='Data Sheet'!B16 -> 42825 | D2: ='Data Sheet'!C16 -> 43190 | E2: ='Data Sheet'!D16 -> 43555 | F2: ='Data Sheet'!E16 -> 43921 | G2: ='Data Sheet'!F16 -> 44286 | H2: ='Data Sheet'!G16 -> 44651 | I2: ='Data Sheet'!H16 -> 45016 | ... L2: ='Data Sheet'!K16 -> 46112 | M2: =L2+365 -> 46477 | N2: =M2+365 -> 46842 | O2: =N2+365 -> 47207 | P2: =O2+365 -> 47572 | Q2: =P2+365 -> 47937
B3: Net Profit Margin | C3: ='Ratios Analysis'!C7 -> 0.2095818 | D3: ='Ratios Analysis'!D7 -> 0.22729077 | E3: ='Ratios Analysis'!E7 -> 0.1863925 | F3: ='Ratios Analysis'!F7 -> 0.18326706 | G3: ='Ratios Analysis'!G7 -> 0.19331754 | H3: ='Ratios Analysis'!H7 -> 0.18206033 | I3: ='Ratios Analysis'!I7 -> 0.16426036 | J3: ='Ratios Analysis'!J7 -> 0.17080757 | ... Q3: ='Ratios Analysis'!Q7 -> 0.18544177
B4: Tax Burden | C4: ='Historical Financial Statement'!C23/'Historical Financial Statement'!C19 -> 0.71941256 | D4: ='Historical Financial Statement'!D23/'Historical Financial Statement'!D19 -> 0.79077454 | E4: ='Historical Financial Statement'!E23/'Historical Financial Statement'!E19 -> 0.73237964 | F4: ='Historical Financial Statement'!F23/'Historical Financial Statement'!F19 -> 0.75607761 | G4: ='Historical Financial Statement'!G23/'Historical Financial Statement'!G19 -> 0.72942016 | H4: ='Historical Financial Statement'!H23/'Historical Financial Statement'!H19 -> 0.73550316 | I4: ='Historical Financial Statement'!I23/'Historical Financial Statement'!I19 -> 0.72348599 | J4: ='Historical Financial Statement'!J23/'Historical Financial Statement'!J19 -> 0.72935423 | ... Q4: ='Historical Financial Statement'!Q23/'Historical Financial Statement'!Q19 -> 0.73064913
B5: Interest Burden | C5: ='Historical Financial Statement'!C19/'Historical Financial Statement'!C14 -> 1.1804627 | D5: ='Historical Financial Statement'!D19/'Historical Financial Statement'!D14 -> 1.1952356 | E5: ='Historical Financial Statement'!E19/'Historical Financial Statement'!E14 -> 1.1587092 | F5: ='Historical Financial Statement'!F19/'Historical Financial Statement'!F14 -> 1.1359038 | G5: ='Historical Financial Statement'!G19/'Historical Financial Statement'!G14 -> 1.0814719 | H5: ='Historical Financial Statement'!H19/'Historical Financial Statement'!H14 -> 1.0747814 | I5: ='Historical Financial Statement'!I19/'Historical Financial Statement'!I14 -> 1.0782074 | J5: ='Historical Financial Statement'!J19/'Historical Financial Statement'!J14 -> 1.1335874 | ... Q5: ='Historical Financial Statement'!Q19/'Historical Financial Statement'!Q14 -> 1.0953679
B6: Operating Margin | C6: ='Ratios Analysis'!C6 -> 0.24678757 | D6: ='Ratios Analysis'!D6 -> 0.24047815 | E6: ='Ratios Analysis'!E6 -> 0.21964318 | F6: ='Ratios Analysis'!F6 -> 0.2133912 | G6: ='Ratios Analysis'!G6 -> 0.2450633 | H6: ='Ratios Analysis'!H6 -> 0.23030886 | I6: ='Ratios Analysis'!I6 -> 0.21057186 | J6: ='Ratios Analysis'!J6 -> 0.20659205 | ... Q6: ='Ratios Analysis'!Q6 -> 0.23170676
B7: Assets Turnover | C7: ='Ratios Analysis'!C19 -> 0.82363977 | D7: ='Ratios Analysis'!D19 -> 0.88875726 | E7: ='Ratios Analysis'!E19 -> 0.98345348 | F7: ='Ratios Analysis'!F19 -> 0.98900871 | G7: ='Ratios Analysis'!G19 -> 0.93452763 | H7: ='Ratios Analysis'!H19 -> 1.0420804 | I7: ='Ratios Analysis'!I19 -> 1.1779431 | J7: ='Ratios Analysis'!J19 -> 1.1297603 | ... Q7: ='Ratios Analysis'!Q19 -> 1.0770442
B8: Equity Multiplier | C8: ='Historical Financial Statement'!C60/SUM('Historical Financial Statement'!C29:C30) -> 1.2053579 | D8: ='Historical Financial Statement'!D60/SUM('Historical Financial Statement'!D29:D30) -> 1.2222017 | E8: ='Historical Financial Statement'!E60/SUM('Historical Financial Statement'!E29:E30) -> 1.2943586 | F8: ='Historical Financial Statement'!F60/SUM('Historical Financial Statement'!F29:F30) -> 1.4025974 | G8: ='Historical Financial Statement'!G60/SUM('Historical Financial Statement'!G29:G30) -> 1.4081152 | H8: ='Historical Financial Statement'!H60/SUM('Historical Financial Statement'!H29:H30) -> 1.5491573 | I8: ='Historical Financial Statement'!I60/SUM('Historical Financial Statement'!I29:I30) -> 1.6523134 | J8: ='Historical Financial Statement'!J60/SUM('Historical Financial Statement'!J29:J30) -> 1.543647 | ... Q8: ='Historical Financial Statement'!Q60/SUM('Historical Financial Statement'!Q29:Q30) -> 1.4790119
B10: DuPont 3 Step Model
B11: Return on Equity | C11: =C3*C7*C8 -> 0.20806877 | D11: =D3*D7*D8 -> 0.24689247 | E11: =E3*E7*E8 -> 0.23726674 | F11: =F3*F7*F8 -> 0.2542246 | G11: =G3*G7*G8 -> 0.25439091 | H11: =H3*H7*H8 -> 0.29390843 | I11: =I3*I7*I8 -> 0.31970507 | J11: =J3*J7*J8 -> 0.29788007 | ... Q11: =Q3*Q7*Q8 -> 0.29540156
B13: DuPont 5 Step Model
B14: Return on Equity | C14: =C4*C5*C6*C7*C8 -> 0.20806877 | D14: =D4*D5*D6*D7*D8 -> 0.24689247 | E14: =E4*E5*E6*E7*E8 -> 0.23726674 | F14: =F4*F5*F6*F7*F8 -> 0.2542246 | G14: =G4*G5*G6*G7*G8 -> 0.25439091 | H14: =H4*H5*H6*H7*H8 -> 0.29390843 | I14: =I4*I5*I6*I7*I8 -> 0.31970507 | J14: =J4*J5*J6*J7*J8 -> 0.29788007 | ... Q14: =Q4*Q5*Q6*Q7*Q8 -> 0.29540156

Sheet BETA Calculation
B1: ="BETA Calculation for "&'Data Sheet'!B1 -> BETA Calculation for INFOSYS LTD
B2: Infosys | F2: Nifty-500
B3: Date | C3: Price | D3: Return | F3: Price | G3: Return
B4: 10/18/2026 | C4: 1153.8 | D4: =IFERROR((C4/C5)-1,0) -> -0.0063727179 | F4: 21696.55 | G4: =IFERROR((F4/F5)-1,0) -> -0.025752075 | I4: Correlation Between Infosys and Nifty-500 | J4: =CORREL(D4:D525,G4:G525) -> 0.40394329 | K4: covariance Between Infosys And Nifty-500 | L4: =_xlfn.COVARIANCE.S(D4:D525,G4:G525) -> 0.00032215851
B5: 46336 | C5: 1161.2 | D5: =IFERROR((C5/C6)-1,0) -> 0.13464921 | F5: 22270.05 | G5: =IFERROR((F5/F6)-1,0) -> 0.018448185 | I5: Standard Deviation of Infosys | J5: =_xlfn.STDEV.S(D4:D525) -> 0.036613198 | K5: Variance of Nifty-500 | L5: =_xlfn.VAR.S(G4:G525) -> 0.00047448565
B6: 46122 | C6: 1023.4 | D6: =IFERROR((C6/C7)-1,0) -> -0.011207729 | F6: 21866.65 | G6: =IFERROR((F6/F7)-1,0) -> 0.00040717823 | I6: Standard Deviation of Nifty-500 | J6: =_xlfn.STDEV.S(G4:G525) -> 0.021782692
B7: 09/27/2026 | C7: 1035 | D7: =IFERROR((C7/C8)-1,0) -> 0.034793041 | F7: 21857.75 | G7: =IFERROR((F7/F8)-1,0) -> -0.032992678
B8: 09/20/2026 | C8: 1000.2 | D8: =IFERROR((C8/C9)-1,0) -> -0.048696975 | F8: 22603.5 | G8: =IFERROR((F8/F9)-1,0) -> -0.010378472 | I8: BETA(L) | J8: =J4*(J5/J6) -> 0.67896364
B9: 09/13/2026 | C9: 1051.4 | D9: =IFERROR((C9/C10)-1,0) -> 0.013202274 | F9: 22840.55 | G9: =IFERROR((F9/F10)-1,0) -> -0.0011348479 | I9: BETA(UL) | J9: =J8/(1+('DCF Model'!C4/'DCF Model'!C3)*(1-'DCF Model'!C9)) -> 0.67000398
B10: 46182 | C10: 1037.7 | D10: =IFERROR((C10/C11)-1,0) -> -0.081681416 | F10: 22866.5 | G10: =IFERROR((F10/F11)-1,0) -> -0.016670143
B11: 08/30/2026 | C11: 1130 | D11: =IFERROR((C11/C12)-1,0) -> -0.012237762 | F11: 23254.15 | G11: =IFERROR((F11/F12)-1,0) -> -0.011662427 | I11: BETA(L) Re-Check | J11: =L4/L5 -> 0.67896364
B12: 08/23/2026 | C12: 1144 | D12: =IFERROR((C12/C13)-1,0) -> 0.020517395 | F12: 23528.55 | G12: =IFERROR((F12/F13)-1,0) -> -7.4372192e-05
B13: 08/16/2026 | C13: 1121 | D13: =IFERROR((C13/C14)-1,0) -> -0.041224769 | F13: 23530.3 | G13: =IFERROR((F13/F14)-1,0) -> -0.0027378798
B14: 46273 | C14: 1169.2 | D14: =IFERROR((C14/C15)-1,0) -> -0.0050208493 | F14: 23594.9 | G14: =IFERROR((F14/F15)-1,0) -> -0.0049426242
B15: 46061 | C15: 1175.1 | D15: =IFERROR((C15/C16)-1,0) -> 0.039819485 | F15: 23712.1 | G15: =IFERROR((F15/F16)-1,0) -> 0.010715793
B16: 07/26/2026 | C16: 1130.1 | D16: =IFERROR((C16/C17)-1,0) -> 0.085695072 | F16: 23460.7 | G16: =IFERROR((F16/F17)-1,0) -> 0.023890055
B17: 07/19/2026 | C17: 1040.9 | D17: =IFERROR((C17/C18)-1,0) -> -0.050706794 | F17: 22913.3 | G17: =IFERROR((F17/F18)-1,0) -> -0.018126267
B18: 46363 | C18: 1096.5 | D18: =IFERROR((C18/C19)-1,0) -> 0.026685393 | F18: 23336.3 | G18: =IFERROR((F18/F19)-1,0) -> -0.0005182368
B19: 46149 | C19: 1068 | D19: =IFERROR((C19/C20)-1,0) -> 0.01986249 | F19: 23348.4 | G19: =IFERROR((F19/F20)-1,0) -> 0.0020277969
B20: 06/28/2026 | C20: 1047.2 | D20: =IFERROR((C20/C21)-1,0) -> 0.0057625816 | F20: 23301.15 | G20: =IFERROR((F20/F21)-1,0) -> 0.0081099088
B21: 06/21/2026 | C21: 1041.2 | D21: =IFERROR((C21/C22)-1,0) -> -0.0097013506 | F21: 23113.7 | G21: =IFERROR((F21/F22)-1,0) -> -0.0013178248
B22: 06/14/2026 | C22: 1051.4 | D22: =IFERROR((C22/C23)-1,0) -> -0.058222859 | F22: 23144.2 | G22: =IFERROR((F22/F23)-1,0) -> 0.024088709
B23: 46209 | C23: 1116.4 | D23: =IFERROR((C23/C24)-1,0) -> -0.067724426 | F23: 22599.8 | G23: =IFERROR((F23/F24)-1,0) -> 0.0059847721
B24: 05/31/2026 | C24: 1197.5 | D24: =IFERROR((C24/C25)-1,0) -> 0.031527263 | F24: 22465.35 | G24: =IFERROR((F24/F25)-1,0) -> -0.0084587545
B25: 05/24/2026 | C25: 1160.9 | D25: =IFERROR((C25/C26)-1,0) -> -0.011579395 | F25: 22657 | G25: =IFERROR((F25/F26)-1,0) -> 0.00025164119
B26: 05/17/2026 | C26: 1174.5 | D26: =IFERROR((C26/C27)-1,0) -> 0.049597855 | F26: 22651.3 | G26: =IFERROR((F26/F27)-1,0) -> 0.0053326173
B27: 46300 | C27: 1119 | D27: =IFERROR((C27/C28)-1,0) -> -0.05105156 | F27: 22531.15 | G27: =IFERROR((F27/F28)-1,0) -> -0.025285899
B28: 46086 | C28: 1179.2 | D28: =IFERROR((C28/C29)-1,0) -> -0.0022000338 | F28: 23115.65 | G28: =IFERROR((F28/F29)-1,0) -> 0.019049047
B29: 04/26/2026 | C29: 1181.8 | D29: =IFERROR((C29/C30)-1,0) -> 0.023557942 | F29: 22683.55 | G29: =IFERROR((F29/F30)-1,0) -> 0.0050287882
B30: 04/19/2026 | C30: 1154.6 | D30: =IFERROR((C30/C31)-1,0) -> -0.12444074 | F30: 22570.05 | G30: =IFERROR((F30/F31)-1,0) -> -0.013089543
B31: 46360 | C31: 1318.7 | D31: =IFERROR((C31/C32)-1,0) -> 0.020270793 | F31: 22869.4 | G31: =IFERROR((F31/F32)-1,0) -> 0.023388188
B32: 46146 | C32: 1292.5 | D32: =IFERROR((C32/C33)-1,0) -> -0.0063806888 | F32: 22346.75 | G32: =IFERROR((F32/F33)-1,0) -> 0.067264135
B33: 03/29/2026 | C33: 1300.8 | D33: =IFERROR((C33/C34)-1,0) -> 0.024493975 | F33: 20938.35 | G33: =IFERROR((F33/F34)-1,0) -> -0.0038915041
B34: 03/22/2026 | C34: 1269.7 | D34: =IFERROR((C34/C35)-1,0) -> 0.010988136 | F34: 21020.15 | G34: =IFERROR((F34/F35)-1,0) -> -0.014429456
B35: 03/15/2026 | C35: 1255.9 | D35: =IFERROR((C35/C36)-1,0) -> 0.0060882801 | F35: 21327.9 | G35: =IFERROR((F35/F36)-1,0) -> -0.0029591608
B36: 46237 | C36: 1248.3 | D36: =IFERROR((C36/C37)-1,0) -> -0.045933965 | F36: 21391.2 | G36: =IFERROR((F36/F37)-1,0) -> -0.048489189
B37: 46025 | C37: 1308.4 | D37: =IFERROR((C37/C38)-1,0) -> 0.0063841243 | F37: 22481.3 | G37: =IFERROR((F37/F38)-1,0) -> -0.029591852
B38: 02/22/2026 | C38: 1300.1 | D38: =IFERROR((C38/C39)-1,0) -> -0.039240319 | F38: 23166.85 | G38: =IFERROR((F38/F39)-1,0) -> -0.0097520838
B39: 02/15/2026 | C39: 1353.2 | D39: =IFERROR((C39/C40)-1,0) -> -0.011613469 | F39: 23395 | G39: =IFERROR((F39/F40)-1,0) -> 0.0035108941
B40: 46236 | C40: 1369.1 | D40: =IFERROR((C40/C41)-1,0) -> -0.091566585 | F40: 23313.15 | G40: =IFERROR((F40/F41)-1,0) -> -0.0051570368
B41: 46024 | C41: 1507.1 | D41: =IFERROR((C41/C42)-1,0) -> -0.081596587 | F41: 23434 | G41: =IFERROR((F41/F42)-1,0) -> 0.015359951
B42: 01/25/2026 | C42: 1641 | D42: =IFERROR((C42/C43)-1,0) -> -0.017835767 | F42: 23079.5 | G42: =IFERROR((F42/F43)-1,0) -> 0.016440444
B43: 01/18/2026 | C43: 1670.8 | D43: =IFERROR((C43/C44)-1,0) -> -0.011243934 | F43: 22706.2 | G43: =IFERROR((F43/F44)-1,0) -> -0.033173943
B44: 46327 | C44: 1689.8 | D44: =IFERROR((C44/C45)-1,0) -> 0.046899201 | F44: 23485.3 | G44: =IFERROR((F44/F45)-1,0) -> 0.0007648925
B45: 46113 | C45: 1614.1 | D45: =IFERROR((C45/C46)-1,0) -> -0.016032675 | F45: 23467.35 | G45: =IFERROR((F45/F46)-1,0) -> -0.026210631
B46: 12/28/2025 | C46: 1640.4 | D46: =IFERROR((C46/C47)-1,0) -> -0.0094801039 | F46: 24099 | G46: =IFERROR((F46/F47)-1,0) -> 0.01340398
B47: 12/21/2025 | C47: 1656.1 | D47: =IFERROR((C47/C48)-1,0) -> 0.010618173 | F47: 23780.25 | G47: =IFERROR((F47/F48)-1,0) -> 0.004337442
B48: 12/14/2025 | C48: 1638.7 | D48: =IFERROR((C48/C49)-1,0) -> 0.025341009 | F48: 23677.55 | G48: =IFERROR((F48/F49)-1,0) -> -0.0020504758
B49: 45850 | C49: 1598.2 | D49: =IFERROR((C49/C50)-1,0) -> -0.011137235 | F49: 23726.2 | G49: =IFERROR((F49/F50)-1,0) -> -0.0045751565
B50: 11/30/2025 | C50: 1616.2 | D50: =IFERROR((C50/C51)-1,0) -> 0.035959233 | F50: 23835.25 | G50: =IFERROR((F50/F51)-1,0) -> -0.0040926412
B51: 11/23/2025 | C51: 1560.1 | D51: =IFERROR((C51/C52)-1,0) -> 0.0097734628 | F51: 23933.2 | G51: =IFERROR((F51/F52)-1,0) -> 0.0060087641
B52: 11/16/2025 | C52: 1545 | D52: =IFERROR((C52/C53)-1,0) -> 0.028080916 | F52: 23790.25 | G52: =IFERROR((F52/F53)-1,0) -> -0.0019340209
B53: 45911 | C53: 1502.8 | D53: =IFERROR((C53/C54)-1,0) -> 0.017605634 | F53: 23836.35 | G53: =IFERROR((F53/F54)-1,0) -> 0.013385626
B54: 45699 | C54: 1476.8 | D54: =IFERROR((C54/C55)-1,0) -> -0.00371045 | F54: 23521.5 | G54: =IFERROR((F54/F55)-1,0) -> -0.0079669681
B55: 10/26/2025 | C55: 1482.3 | D55: =IFERROR((C55/C56)-1,0) -> -0.028254884 | F55: 23710.4 | G55: =IFERROR((F55/F56)-1,0) -> 0.0010047875
B56: 10/19/2025 | C56: 1525.4 | D56: =IFERROR((C56/C57)-1,0) -> 0.058496981 | F56: 23686.6 | G56: =IFERROR((F56/F57)-1,0) -> 0.0037524287
B57: 46001 | C57: 1441.1 | D57: =IFERROR((C57/C58)-1,0) -> -0.048716087 | F57: 23598.05 | G57: =IFERROR((F57/F58)-1,0) -> 0.011162269
B58: 45787 | C58: 1514.9 | D58: =IFERROR((C58/C59)-1,0) -> 0.047214157 | F58: 23337.55 | G58: =IFERROR((F58/F59)-1,0) -> 0.013455534
B59: 09/28/2025 | C59: 1446.6 | D59: =IFERROR((C59/C60)-1,0) -> -0.0015874111 | F59: 23027.7 | G59: =IFERROR((F59/F60)-1,0) -> 0.013848806
B60: 09/21/2025 | C60: 1448.9 | D60: =IFERROR((C60/C61)-1,0) -> -0.059278016 | F60: 22713.15 | G60: =IFERROR((F60/F61)-1,0) -> -0.032933603
B61: 09/14/2025 | C61: 1540.2 | D61: =IFERROR((C61/C62)-1,0) -> 0.0095700052 | F61: 23486.65 | G61: =IFERROR((F61/F62)-1,0) -> 0.012781233
B62: 45847 | C62: 1525.6 | D62: =IFERROR((C62/C63)-1,0) -> 0.056070885 | F62: 23190.25 | G62: =IFERROR((F62/F63)-1,0) -> 0.015817496
B63: 08/31/2025 | C63: 1444.6 | D63: =IFERROR((C63/C64)-1,0) -> -0.017011432 | F63: 22829.15 | G63: =IFERROR((F63/F64)-1,0) -> 0.0163024
B64: 08/24/2025 | C64: 1469.6 | D64: =IFERROR((C64/C65)-1,0) -> -0.012033613 | F64: 22462.95 | G64: =IFERROR((F64/F65)-1,0) -> -0.022980432
B65: 08/17/2025 | C65: 1487.5 | D65: =IFERROR((C65/C66)-1,0) -> 0.027491884 | F65: 22991.3 | G65: =IFERROR((F65/F66)-1,0) -> 0.013714575
B66: 45938 | C66: 1447.7 | D66: =IFERROR((C66/C67)-1,0) -> 0.017286206 | F66: 22680.25 | G66: =IFERROR((F66/F67)-1,0) -> 0.010564471
B67: 45724 | C67: 1423.1 | D67: =IFERROR((C67/C68)-1,0) -> -0.031641263 | F67: 22443.15 | G67: =IFERROR((F67/F68)-1,0) -> -0.010165986
B68: 07/27/2025 | C68: 1469.6 | D68: =IFERROR((C68/C69)-1,0) -> -0.03041499 | F68: 22673.65 | G68: =IFERROR((F68/F69)-1,0) -> -0.01482307
B69: 07/20/2025 | C69: 1515.7 | D69: =IFERROR((C69/C70)-1,0) -> -0.0443856 | F69: 23014.8 | G69: =IFERROR((F69/F70)-1,0) -> -0.01118575
B70: 07/13/2025 | C70: 1586.1 | D70: =IFERROR((C70/C71)-1,0) -> -0.0055175873 | F70: 23275.15 | G70: =IFERROR((F70/F71)-1,0) -> -0.00032427511
B71: 45815 | C71: 1594.9 | D71: =IFERROR((C71/C72)-1,0) -> -0.027914914 | F71: 23282.7 | G71: =IFERROR((F71/F72)-1,0) -> -0.011872704
B72: 06/29/2025 | C72: 1640.7 | D72: =IFERROR((C72/C73)-1,0) -> 0.020335821 | F72: 23562.45 | G72: =IFERROR((F72/F73)-1,0) -> -0.0024428295
B73: 06/22/2025 | C73: 1608 | D73: =IFERROR((C73/C74)-1,0) -> -0.0091810956 | F73: 23620.15 | G73: =IFERROR((F73/F74)-1,0) -> 0.025131179
B74: 06/15/2025 | C74: 1622.9 | D74: =IFERROR((C74/C75)-1,0) -> 0.013046192 | F74: 23041.1 | G74: =IFERROR((F74/F75)-1,0) -> 0.0058892352
B75: 45875 | C75: 1602 | D75: =IFERROR((C75/C76)-1,0) -> 0.024427676 | F75: 22906.2 | G75: =IFERROR((F75/F76)-1,0) -> -0.011176295
B76: 45663 | C76: 1563.8 | D76: =IFERROR((C76/C77)-1,0) -> 0.0007039099 | F76: 23165.1 | G76: =IFERROR((F76/F77)-1,0) -> 0.015926269
B77: 05/25/2025 | C77: 1562.7 | D77: =IFERROR((C77/C78)-1,0) -> -0.0013420245 | F77: 22801.95 | G77: =IFERROR((F77/F78)-1,0) -> 0.00091742918
B78: 05/18/2025 | C78: 1564.8 | D78: =IFERROR((C78/C79)-1,0) -> -0.015787156 | F78: 22781.05 | G78: =IFERROR((F78/F79)-1,0) -> -0.003928573
B79: 45966 | C79: 1589.9 | D79: =IFERROR((C79/C80)-1,0) -> 0.054590077 | F79: 22870.9 | G79: =IFERROR((F79/F80)-1,0) -> 0.05514739
B80: 45752 | C80: 1507.6 | D80: =IFERROR((C80/C81)-1,0) -> 0.00053092647 | F80: 21675.55 | G80: =IFERROR((F80/F81)-1,0) -> -0.015016359
B81: 04/27/2025 | C81: 1506.8 | D81: =IFERROR((C81/C82)-1,0) -> 0.017970545 | F81: 22006 | G81: =IFERROR((F81/F82)-1,0) -> 0.007224868
B82: 04/20/2025 | C82: 1480.2 | D82: =IFERROR((C82/C83)-1,0) -> 0.042761536 | F82: 21848.15 | G82: =IFERROR((F82/F83)-1,0) -> 0.0076839525
B83: 04/13/2025 | C83: 1419.5 | D83: =IFERROR((C83/C84)-1,0) -> 0.007130441 | F83: 21681.55 | G83: =IFERROR((F83/F84)-1,0) -> 0.04475048
B84: 45812 | C84: 1409.45 | D84: =IFERROR((C84/C85)-1,0) -> -0.029070368 | F84: 20752.85 | G84: =IFERROR((F84/F85)-1,0) -> -0.0025233894
B85: 03/30/2025 | C85: 1451.65 | D85: =IFERROR((C85/C86)-1,0) -> -0.075764811 | F85: 20805.35 | G85: =IFERROR((F85/F86)-1,0) -> -0.02503333
B86: 03/23/2025 | C86: 1570.65 | D86: =IFERROR((C86/C87)-1,0) -> -0.013751531 | F86: 21339.55 | G86: =IFERROR((F86/F87)-1,0) -> 0.003085941
B87: 03/16/2025 | C87: 1592.55 | D87: =IFERROR((C87/C88)-1,0) -> 0.0080387379 | F87: 21273.9 | G87: =IFERROR((F87/F88)-1,0) -> 0.054413525
B88: 45903 | C88: 1579.85 | D88: =IFERROR((C88/C89)-1,0) -> -0.062959668 | F88: 20176.05 | G88: =IFERROR((F88/F89)-1,0) -> -0.01307757
B89: 45691 | C89: 1686 | D89: =IFERROR((C89/C90)-1,0) -> -0.001007288 | F89: 20443.4 | G89: =IFERROR((F89/F90)-1,0) -> 0.028293488
B90: 02/23/2025 | C90: 1687.7 | D90: =IFERROR((C90/C91)-1,0) -> -0.070137741 | F90: 19880.9 | G90: =IFERROR((F90/F91)-1,0) -> -0.039117459
B91: 02/16/2025 | C91: 1815 | D91: =IFERROR((C91/C92)-1,0) -> -0.022301228 | F91: 20690.25 | G91: =IFERROR((F91/F92)-1,0) -> 0.0027698213
B92: 45902 | C92: 1856.4 | D92: =IFERROR((C92/C93)-1,0) -> -0.024820739 | F92: 20633.1 | G92: =IFERROR((F92/F93)-1,0) -> -0.04680047
B93: 45690 | C93: 1903.65 | D93: =IFERROR((C93/C94)-1,0) -> 0.01268752 | F93: 21646.15 | G93: =IFERROR((F93/F94)-1,0) -> 0.0030235069
B94: 01/26/2025 | C94: 1879.8 | D94: =IFERROR((C94/C95)-1,0) -> 0.0023194433 | F94: 21580.9 | G94: =IFERROR((F94/F95)-1,0) -> 0.012289565
B95: 01/19/2025 | C95: 1875.45 | D95: =IFERROR((C95/C96)-1,0) -> 0.033049657 | F95: 21318.9 | G95: =IFERROR((F95/F96)-1,0) -> -0.016667243
B96: 45992 | C96: 1815.45 | D96: =IFERROR((C96/C97)-1,0) -> -0.077022802 | F96: 21680.25 | G96: =IFERROR((F96/F97)-1,0) -> -0.0054474976
B97: 45778 | C97: 1966.95 | D97: =IFERROR((C97/C98)-1,0) -> 0.014545455 | F97: 21799 | G97: =IFERROR((F97/F98)-1,0) -> -0.040036287
B98: 12/29/2024 | C98: 1938.75 | D98: =IFERROR((C98/C99)-1,0) -> 0.011477762 | F98: 22708.15 | G98: =IFERROR((F98/F99)-1,0) -> 0.0117152
B99: 12/22/2024 | C99: 1916.75 | D99: =IFERROR((C99/C100)-1,0) -> -0.0028093541 | F99: 22445.2 | G99: =IFERROR((F99/F100)-1,0) -> 0.0056363522
B100: 12/15/2024 | C100: 1922.15 | D100: =IFERROR((C100/C101)-1,0) -> -0.038780817 | F100: 22319.4 | G100: =IFERROR((F100/F101)-1,0) -> -0.044503285
...

Sheet Calculation
A1: * | B1: ="Calculation for "&'Data Sheet'!B1 -> Calculation for INFOSYS LTD
B2: ='Data Sheet'!A16 -> Report Date | C2: ='Data Sheet'!B16 -> 42825 | D2: ='Data Sheet'!C16 -> 43190 | E2: ='Data Sheet'!D16 -> 43555 | F2: ='Data Sheet'!E16 -> 43921 | G2: ='Data Sheet'!F16 -> 44286 | H2: ='Data Sheet'!G16 -> 44651 | I2: ='Data Sheet'!H16 -> 45016 | ... L2: ='Data Sheet'!K16 -> 46112 | M2: =L2+365 -> 46477 | N2: =M2+365 -> 46842 | O2: =N2+365 -> 47207 | P2: =O2+365 -> 47572 | Q2: =P2+365 -> 47937 | S2: 46477 | T2: 46842 | U2: 47207 | V2: 47572 | W2: 47937
B3: ='Historical Financial Statement'!B3 -> Sales | C3: ='Historical Financial Statement'!C3 -> 68484 | D3: ='Historical Financial Statement'!D3 -> 70522 | E3: ='Historical Financial Statement'!E3 -> 82675 | F3: ='Historical Financial Statement'!F3 -> 90791 | G3: ='Historical Financial Statement'!G3 -> 100472 | H3: ='Historical Financial Statement'!H3 -> 121641 | I3: ='Historical Financial Statement'!I3 -> 146767 | ... L3: ='Historical Financial Statement'!L3 -> 178650 | M3: =L3*(1+$C4) -> 196627.57 | N3: =M3*(1+$C4) -> 216414.22 | O3: =N3*(1+$C4) -> 238192.01 | P3: =O3*(1+$C4) -> 262161.3 | Q3: =P3*(1+$C4) -> 288542.62 | S3: Fixed Assets Schedule
B4: CAGR | C4: =_xlfn.RRI(10,C3,L3) -> 0.10063011 | S4: =L18 -> 33770 | T4: =S7 -> 33664.389 | U4: =T7 -> 33604.963 | V4: =U7 -> 33891.802 | W4: =V7 -> 34381.206
S5: =-M19 -> -4711.642 | T5: =-N19 -> -4763.7377 | U5: =-O19 -> -4733.8014 | V5: =-P19 -> -4813.7466 | W5: =-Q19 -> -4946.5198
B6: ='Historical Financial Statement'!B4 -> COGS | C6: ='Historical Financial Statement'!C4 -> 44609 | D6: ='Historical Financial Statement'!D4 -> 46395 | E6: ='Historical Financial Statement'!E4 -> 55446 | F6: ='Historical Financial Statement'!F4 -> 62210 | G6: ='Historical Financial Statement'!G4 -> 68490 | H6: ='Historical Financial Statement'!H4 -> 84819 | I6: ='Historical Financial Statement'!I4 -> 104880 | ... L6: ='Historical Financial Statement'!L4 -> 128257 | M6: =M3*C8 -> 135828.55 | N6: =N3*D8 -> 150349.94 | O6: =O3*E8 -> 166357.47 | P6: =P3*F8 -> 183825.99 | Q6: =Q3*G8 -> 202785.92 | S6: =M24 -> 4606.0312 | T6: =N24 -> 4704.311 | U6: =O24 -> 5020.6413 | V6: =P24 -> 5303.1497 | W6: =Q24 -> 5369.4902
B7: % COGS | C7: =C6/C3 -> 0.65137842 | D7: =D6/D3 -> 0.65787981 | E7: =E6/E3 -> 0.67065014 | F7: =F6/F3 -> 0.68520007 | G7: =G6/G3 -> 0.68168246 | H7: =H6/H3 -> 0.69728957 | I7: =I6/I3 -> 0.71460206 | J7: =J6/J3 -> 0.71601484 | ... Q7: =Q6/Q3 -> 0.70279365 | S7: =SUM(S4:S6) -> 33664.389 | T7: =SUM(T4:T6) -> 33604.963 | U7: =SUM(U4:U6) -> 33891.802 | V7: =SUM(V4:V6) -> 34381.206 | W7: =SUM(W4:W6) -> 34804.176
B8: Average | C8: =AVERAGE(C7:L7) -> 0.690791 | D8: =AVERAGE(D7:M7) -> 0.69473225 | E8: =AVERAGE(E7:N7) -> 0.6984175 | F8: =AVERAGE(F7:O7) -> 0.70119423 | G8: =AVERAGE(G7:P7) -> 0.70279365
B10: ='Historical Financial Statement'!B8 -> Selling and admin | C10: ='Historical Financial Statement'!C8 -> 4584 | D10: ='Historical Financial Statement'!D8 -> 4585 | E10: ='Historical Financial Statement'!E8 -> 5553 | F10: ='Historical Financial Statement'!F8 -> 5375 | G10: ='Historical Financial Statement'!G8 -> 3194 | H10: ='Historical Financial Statement'!H8 -> 4305 | I10: ='Historical Financial Statement'!I8 -> 5300 | ... L10: ='Historical Financial Statement'!L8 -> 6784 | M10: =M3*C12 -> 9315.4617 | N10: =N3*D12 -> 9829.5894 | O10: =O3*E12 -> 10352.007 | P10: =P3*F12 -> 10772.255 | Q10: =Q3*G12 -> 11333.667 | S10: Resevers Schedule
B11: % Selling and admin | C11: =C10/C3 -> 0.066935343 | D11: =D10/D3 -> 0.065015173 | E11: =E10/E3 -> 0.067166616 | F11: =F10/F3 -> 0.059201903 | G11: =G10/G3 -> 0.031789951 | H11: =H10/H3 -> 0.035391028 | I11: =I10/I3 -> 0.03611166 | J11: =J10/J3 -> 0.037125008 | ... Q11: =Q10/Q3 -> 0.039279006 | S11: ='Historical Financial Statement'!L30 -> 90828 | T11: =S14 -> 105689.07 | U11: =T14 -> 121516.54 | V11: =U14 -> 138075.35 | W11: =V14 -> 157662.03
B12: Average % | C12: =AVERAGE(C11:L11) -> 0.047376173 | D12: =AVERAGE(D11:M11) -> 0.045420256 | E12: =AVERAGE(E11:N11) -> 0.043460764 | F12: =AVERAGE(F11:O11) -> 0.041090179 | G12: =AVERAGE(G11:P11) -> 0.039279006 | S12: =+'Historical Financial Statement'!M23 -> 36936.321 | T12: =+'Historical Financial Statement'!N23 -> 40487.474 | U12: =+'Historical Financial Statement'!O23 -> 43971.496 | V12: =+'Historical Financial Statement'!P23 -> 48581.185 | W12: =+'Historical Financial Statement'!Q23 -> 53507.855
S13: =-M45 -> -22075.25 | T13: =-N45 -> -24660.004 | U13: =-O45 -> -27412.689 | V13: =-P45 -> -28994.5 | W13: =-Q45 -> -32057.894
B14: ='Historical Financial Statement'!B9 -> Other Expenses | C14: ='Historical Financial Statement'!C9 -> 687 | D14: ='Historical Financial Statement'!D9 -> 720 | E14: ='Historical Financial Statement'!E9 -> 1506 | F14: ='Historical Financial Statement'!F9 -> 939 | G14: ='Historical Financial Statement'!G9 -> 899 | H14: ='Historical Financial Statement'!H9 -> 1026 | I14: ='Historical Financial Statement'!I9 -> 1457 | ... L14: ='Historical Financial Statement'!L9 -> 1329 | M14: =M3*C16 -> 1972.322 | N14: =N3*D16 -> 2170.7799 | O14: =O3*E16 -> 2384.9643 | P14: =P3*F16 -> 2409.9093 | Q14: =Q3*G16 -> 2619.2373 | S14: =SUM(S11:S13) -> 105689.07 | T14: =SUM(T11:T13) -> 121516.54 | U14: =SUM(U11:U13) -> 138075.35 | V14: =SUM(V11:V13) -> 157662.03 | W14: =SUM(W11:W13) -> 179111.99
B15: % Other Expenses | C15: =C14/C3 -> 0.01003154 | D15: =D14/D3 -> 0.01020958 | E15: =E14/E3 -> 0.018215906 | F15: =F14/F3 -> 0.010342435 | G15: =G14/G3 -> 0.0089477665 | H15: =H14/H3 -> 0.0084346561 | I15: =I14/I3 -> 0.0099272997 | J15: =J14/J3 -> 0.0098262511 | ... Q15: =Q14/Q3 -> 0.009077471
B16: Average % | C16: =AVERAGE(C15:L15) -> 0.01003075 | D16: =AVERAGE(D15:M15) -> 0.010030671 | E16: =AVERAGE(E15:N15) -> 0.01001278 | F16: =AVERAGE(F15:O15) -> 0.0091924677 | G16: =AVERAGE(G15:P15) -> 0.009077471
B18: ='Historical Financial Statement'!B48 -> Net Block | C18: ='Historical Financial Statement'!C48 -> 14179 | D18: ='Historical Financial Statement'!D48 -> 12574 | E18: ='Historical Financial Statement'!E48 -> 15710 | F18: ='Historical Financial Statement'!F48 -> 23789 | G18: ='Historical Financial Statement'!G48 -> 25505 | H18: ='Historical Financial Statement'!H48 -> 25800 | I18: ='Historical Financial Statement'!I48 -> 29225 | ... L18: ='Historical Financial Statement'!L48 -> 33770 | M18: =S7 -> 33664.389 | N18: =T7 -> 33604.963 | O18: =U7 -> 33891.802 | P18: =V7 -> 34381.206 | Q18: =W7 -> 34804.176 | S18: Debt Schedule
B19: ='Historical Financial Statement'!B13 -> Depreciation | C19: ='Historical Financial Statement'!C13 -> 1703 | D19: ='Historical Financial Statement'!D13 -> 1863 | E19: ='Historical Financial Statement'!E13 -> 2011 | F19: ='Historical Financial Statement'!F13 -> 2893 | G19: ='Historical Financial Statement'!G13 -> 3267 | H19: ='Historical Financial Statement'!H13 -> 3476 | I19: ='Historical Financial Statement'!I13 -> 4225 | ... L19: ='Historical Financial Statement'!L13 -> 4902 | M19: =L18*C21 -> 4711.642 | N19: =M18*D21 -> 4763.7377 | O19: =N18*E21 -> 4733.8014 | P19: =O18*F21 -> 4813.7466 | Q19: =P18*G21 -> 4946.5198 | S19: =L28 -> 9176 | T19: =S23 -> 9176 | U19: =T23 -> 9176 | V19: =U23 -> 9176 | W19: =V23 -> 9176
B20: % Depreciation | C20: =C19/C18 -> 0.1201072 | D20: =D19/D18 -> 0.14816288 | E20: =E19/E18 -> 0.12800764 | F20: =F19/F18 -> 0.12161083 | G20: =G19/G18 -> 0.12809253 | H20: =H19/H18 -> 0.13472868 | I20: =I19/I18 -> 0.14456801 | J20: =J19/J18 -> 0.16935776 | ... Q20: =Q19/Q18 -> 0.14212432 | S20: ='Historical Financial Statement'!$S21 -> 0 | T20: ='Historical Financial Statement'!$S21 -> 0 | U20: ='Historical Financial Statement'!$S21 -> 0 | V20: ='Historical Financial Statement'!$S21 -> 0 | W20: ='Historical Financial Statement'!$S21 -> 0
B21: Average % | C21: =AVERAGE(C20:L20) -> 0.13952153 | D21: =AVERAGE(D20:M20) -> 0.14150673 | E21: =AVERAGE(E20:N20) -> 0.14086614 | F21: =AVERAGE(F20:O20) -> 0.14203277 | G21: =AVERAGE(G20:P20) -> 0.14387279 | S21: ='Historical Financial Statement'!$L89 -> -2824 | T21: ='Historical Financial Statement'!$L89 -> -2824 | U21: ='Historical Financial Statement'!$L89 -> -2824 | V21: ='Historical Financial Statement'!$L89 -> -2824 | W21: ='Historical Financial Statement'!$L89 -> -2824
S22: =-S21 -> 2824 | T22: =-T21 -> 2824 | U22: =-U21 -> 2824 | V22: =-V21 -> 2824 | W22: =-W21 -> 2824
S23: =SUM(S19:S22) -> 9176 | T23: =SUM(T19:T22) -> 9176 | U23: =SUM(U19:U22) -> 9176 | V23: =SUM(V19:V22) -> 9176 | W23: =SUM(W19:W22) -> 9176
B24: ='Manual Data'!B14 -> Fixed assets purchased | C24: =-'Manual Data'!C14 -> 2760 | D24: =-'Manual Data'!D14 -> 1998 | E24: =-'Manual Data'!E14 -> 2445 | F24: =-'Manual Data'!F14 -> 3307 | G24: =-'Manual Data'!G14 -> 2107 | H24: =-'Manual Data'!H14 -> 2161 | I24: =-'Manual Data'!I14 -> 2579 | J24: =-'Manual Data'!J14 -> 2201 | ... L24: =-'Manual Data'!L14 -> 2727 | M24: =M3*C26 -> 4606.0312 | N24: =N3*D26 -> 4704.311 | O24: =O3*E26 -> 5020.6413 | P24: =P3*F26 -> 5303.1497 | Q24: =Q3*G26 -> 5369.4902 | S24: =AVERAGE(S19,S23)*C31 -> 271.79132 | T24: =AVERAGE(T19,T23)*D31 -> 298.97046 | U24: =AVERAGE(U19,U23)*E31 -> 328.8675 | V24: =AVERAGE(V19,V23)*F31 -> 361.75425 | W24: =AVERAGE(W19,W23)*G31 -> 364.25992
B25: % Fixed Assets purchased | C25: =C24/C3 -> 0.040301384 | D25: =D24/D3 -> 0.028331584 | E25: =E24/E3 -> 0.029573632 | F25: =F24/F3 -> 0.036424315 | G25: =G24/G3 -> 0.020971017 | H25: =H24/H3 -> 0.017765392 | I25: =I24/I3 -> 0.01757207 | J25: =J24/J3 -> 0.0143229 | ... Q25: =Q24/Q3 -> 0.018609002
B26: Average % | C26: =AVERAGE(C25:L25) -> 0.023425155 | D26: =AVERAGE(D25:M25) -> 0.021737532 | E26: =AVERAGE(E25:N25) -> 0.021078126 | F26: =AVERAGE(F25:O25) -> 0.020228576 | G26: =AVERAGE(G25:P25) -> 0.018609002
B28: ='Historical Financial Statement'!B34 -> Borrowings | C28: ='Historical Financial Statement'!C34 -> 0 | D28: ='Historical Financial Statement'!D34 -> 0 | E28: ='Historical Financial Statement'!E34 -> 0 | F28: ='Historical Financial Statement'!F34 -> 4633 | G28: ='Historical Financial Statement'!G34 -> 5325 | H28: ='Historical Financial Statement'!H34 -> 5474 | I28: ='Historical Financial Statement'!I34 -> 8299 | ... L28: ='Historical Financial Statement'!L34 -> 9176 | M28: =S23 -> 9176 | N28: =T23 -> 9176 | O28: =U23 -> 9176 | P28: =V23 -> 9176 | Q28: =W23 -> 9176
B29: ='Historical Financial Statement'!B17 -> Interest | C29: ='Historical Financial Statement'!C17 -> 0 | D29: ='Historical Financial Statement'!D17 -> 0 | E29: ='Historical Financial Statement'!E17 -> 0 | F29: ='Historical Financial Statement'!F17 -> 170 | G29: ='Historical Financial Statement'!G17 -> 195 | H29: ='Historical Financial Statement'!H17 -> 200 | I29: ='Historical Financial Statement'!I17 -> 284 | ... L29: ='Historical Financial Statement'!L17 -> 416 | M29: =S24 -> 271.79132 | N29: =T24 -> 298.97046 | O29: =U24 -> 328.8675 | P29: =V24 -> 361.75425 | Q29: =W24 -> 364.25992
B30: % Interest | C30: =IFERROR(C29/C28,0) -> 0 | D30: =IFERROR(D29/D28,0) -> 0 | E30: =IFERROR(E29/E28,0) -> 0 | F30: =IFERROR(F29/F28,0) -> 0.036693287 | G30: =IFERROR(G29/G28,0) -> 0.036619718 | H30: =IFERROR(H29/H28,0) -> 0.036536354 | I30: =IFERROR(I29/I28,0) -> 0.03422099 | J30: =IFERROR(J29/J28,0) -> 0.056226821 | ... Q30: =IFERROR(Q29/Q28,0) -> 0.039697027
B31: Average % | C31: =IFERROR(AVERAGE(C30:L30),0) -> 0.029619804 | D31: =IFERROR(AVERAGE(D30:M30),0) -> 0.032581785 | E31: =IFERROR(AVERAGE(E30:N30),0) -> 0.035839963 | F31: =IFERROR(AVERAGE(F30:O30),0) -> 0.039423959 | G31: =IFERROR(AVERAGE(G30:P30),0) -> 0.039697027
R32: ='Historical Financial Statement'!R17 -> 0
B36: ='Historical Financial Statement'!B18 -> Other Income | C36: ='Historical Financial Statement'!C18 -> 3050 | D36: ='Historical Financial Statement'!D18 -> 3311 | E36: ='Historical Financial Statement'!E18 -> 2882 | F36: ='Historical Financial Statement'!F18 -> 2803 | G36: ='Historical Financial Statement'!G18 -> 2201 | H36: ='Historical Financial Statement'!H18 -> 2295 | I36: ='Historical Financial Statement'!I18 -> 2701 | ... L36: ='Historical Financial Statement'!L18 -> 3033 | M36: =M3*C38 -> 5625.8377 | N36: =N3*D38 -> 5847.3417 | O36: =O3*E38 -> 5961.0275 | P36: =P3*F38 -> 6303.0967 | Q36: =Q3*G38 -> 6740.2952
B37: % Other Income | C37: =C36/C3 -> 0.04453595 | D37: =D36/D3 -> 0.046949888 | E37: =E36/E3 -> 0.034859389 | F37: =F36/F3 -> 0.030873104 | G37: =G36/G3 -> 0.021906601 | H37: =H36/H3 -> 0.018866994 | I37: =I36/I3 -> 0.01840332 | J37: =J36/J3 -> 0.030656602 | ... Q37: =Q36/Q3 -> 0.023359791
B38: Average % | C38: =AVERAGE(C37:L37) -> 0.028611642 | D38: =AVERAGE(D37:M37) -> 0.027019211 | E38: =AVERAGE(E37:N37) -> 0.025026144 | F38: =AVERAGE(F37:O37) -> 0.024042819 | G38: =AVERAGE(G37:P37) -> 0.023359791
B40: ='Historical Financial Statement'!B19 -> EBT | C40: ='Historical Financial Statement'!C19 -> 19951 | D40: ='Historical Financial Statement'!D19 -> 20270 | E40: ='Historical Financial Statement'!E19 -> 21041 | F40: ='Historical Financial Statement'!F19 -> 22007 | G40: ='Historical Financial Statement'!G19 -> 26628 | H40: ='Historical Financial Statement'!H19 -> 30110 | I40: ='Historical Financial Statement'!I19 -> 33322 | ... Q40: ='Historical Financial Statement'!Q19 -> 73233.31
B41: ='Historical Financial Statement'!B22 -> Tax | C41: ='Historical Financial Statement'!C22 -> 5598 | D41: ='Historical Financial Statement'!D22 -> 4241 | E41: ='Historical Financial Statement'!E22 -> 5631 | F41: ='Historical Financial Statement'!F22 -> 5368 | G41: ='Historical Financial Statement'!G22 -> 7205 | H41: ='Historical Financial Statement'!H22 -> 7964 | I41: ='Historical Financial Statement'!I22 -> 9214 | ... L41: ='Historical Financial Statement'!L22 -> 10521 | M41: =M40*C43 -> 13217.314 | N41: =N40*D43 -> 14361.073 | O41: =O40*E43 -> 16024.434 | P41: =P40*F43 -> 17699.555 | Q41: =Q40*G43 -> 19725.456
B42: % Tax | C42: =C41/C40 -> 0.28058744 | D42: =D41/D40 -> 0.20922546 | E42: =E41/E40 -> 0.26762036 | F42: =F41/F40 -> 0.24392239 | G42: =G41/G40 -> 0.27057984 | H42: =H41/H40 -> 0.26449684 | I42: =I41/I40 -> 0.27651401 | J42: =J41/J40 -> 0.27064577 | ... Q42: =Q41/Q40 -> 0.26935087
B43: Average % | C43: =AVERAGE(C42:L42) -> 0.26353652 | D43: =AVERAGE(D42:M42) -> 0.26183142 | E43: =AVERAGE(E42:N42) -> 0.26709202 | F43: =AVERAGE(F42:O42) -> 0.26703919 | G43: =AVERAGE(G42:P42) -> 0.26935087
B45: ='Historical Financial Statement'!B88 -> Dividends paid | C45: =-'Historical Financial Statement'!C88 -> 6939 | D45: =-'Historical Financial Statement'!D88 -> 7464 | E45: =-'Historical Financial Statement'!E88 -> 13705 | F45: =-'Historical Financial Statement'!F88 -> 9548 | G45: =-'Historical Financial Statement'!G88 -> 9137 | H45: =-'Historical Financial Statement'!H88 -> 12731 | I45: =-'Historical Financial Statement'!I88 -> 13653 | J45: =-'Historical Financial Statement'!J88 -> 14731 | ... L45: =-'Historical Financial Statement'!L88 -> 18656 | M45: =C47*'Historical Financial Statement'!M23 -> 22075.25 | N45: =D47*'Historical Financial Statement'!N23 -> 24660.004 | O45: =E47*'Historical Financial Statement'!O23 -> 27412.689 | P45: =F47*'Historical Financial Statement'!P23 -> 28994.5 | Q45: =G47*'Historical Financial Statement'!Q23 -> 32057.894
B46: Dividends Payout | C46: =C45/'Historical Financial Statement'!C23 -> 0.48345294 | D46: =D45/'Historical Financial Statement'!D23 -> 0.465656 | E46: =E45/'Historical Financial Statement'!E23 -> 0.88935756 | F46: =F45/'Historical Financial Statement'!F23 -> 0.57383256 | G46: =G45/'Historical Financial Statement'!G23 -> 0.47042167 | H46: =H45/'Historical Financial Statement'!H23 -> 0.57486679 | I46: =I45/'Historical Financial Statement'!I23 -> 0.56632653 | J46: =J45/'Historical Financial Statement'!J23 -> 0.56122371 | ... Q46: =Q45/'Historical Financial Statement'!Q23 -> 0.59912502
B47: Average Dividends Payout | C47: =AVERAGE(C46:L46) -> 0.59765697 | D47: =AVERAGE(D46:M46) -> 0.60907737 | E47: =AVERAGE(E46:N46) -> 0.62341951 | F47: =AVERAGE(F46:O46) -> 0.59682571 | G47: =AVERAGE(G46:P46) -> 0.59912502
B49: ='Historical Financial Statement'!B35 -> Other Liabilities | C49: ='Historical Financial Statement'!C35 -> 13799 | D49: ='Historical Financial Statement'!D35 -> 13732 | E49: ='Historical Financial Statement'!E35 -> 17463 | F49: ='Historical Financial Statement'!F35 -> 18865 | G49: ='Historical Financial Statement'!G35 -> 23190 | H49: ='Historical Financial Statement'!H35 -> 31771 | I49: ='Historical Financial Statement'!I35 -> 37025 | ... L49: ='Historical Financial Statement'!L35 -> 47516 | M49: =M3*C51 -> 45222.947 | N49: =N3*D51 -> 50390.531 | O49: =O3*E51 -> 56369.409 | P49: =P3*F51 -> 62708.562 | Q49: =Q3*G51 -> 69925.345
B50: % Other Liabilities | C50: =C49/C3 -> 0.20149232 | D50: =D49/D3 -> 0.19471938 | E50: =E49/E3 -> 0.21122467 | F50: =F49/F3 -> 0.20778491 | G50: =G49/G3 -> 0.23081057 | H50: =H49/H3 -> 0.26118661 | I50: =I49/I3 -> 0.25227061 | J50: =J49/J3 -> 0.23159367 | ... Q50: =Q49/Q3 -> 0.24233974
B51: Average % | C51: =AVERAGE(C50:L50) -> 0.22999291 | D51: =AVERAGE(D50:M50) -> 0.23284297 | E51: =AVERAGE(E50:N50) -> 0.23665533 | F51: =AVERAGE(F50:O50) -> 0.2391984 | G51: =AVERAGE(G50:P50) -> 0.24233974
B54: ='Historical Financial Statement'!B39 -> Trade Payables | C54: ='Historical Financial Statement'!C39 -> 367 | D54: ='Historical Financial Statement'!D39 -> 694 | E54: ='Historical Financial Statement'!E39 -> 1655 | F54: ='Historical Financial Statement'!F39 -> 2852 | G54: ='Historical Financial Statement'!G39 -> 2645 | H54: ='Historical Financial Statement'!H39 -> 4134 | I54: ='Historical Financial Statement'!I39 -> 3865 | ... L54: ='Historical Financial Statement'!L39 -> 4744 | M54: =(C56*M6)/365 -> 4506.0732 | N54: =(D56*N6)/365 -> 5362.9041 | O54: =(E56*O6)/365 -> 6278.4267 | P54: =(F56*P6)/365 -> 7082.7691 | Q54: =(G56*Q6)/365 -> 7664.9531
B55: Days | C55: =365/(C6/C54) -> 3.0028694 | D55: =365/(D6/D54) -> 5.4598556 | E55: =365/(E6/E54) -> 10.894835 | F55: =365/(F6/F54) -> 16.733323 | G55: =365/(G6/G54) -> 14.095853 | H55: =365/(H6/H54) -> 17.789764 | I55: =365/(I6/I54) -> 13.450849 | J55: =365/(J6/J54) -> 13.123148 | ... Q55: =365/(Q6/Q54) -> 13.796362
B56: Average Days | C56: =AVERAGE(C55:L55) -> 12.10877 | D56: =AVERAGE(D55:M55) -> 13.01936 | E56: =AVERAGE(E55:N55) -> 13.77531 | F56: =AVERAGE(F55:O55) -> 14.063358 | G56: =AVERAGE(G55:P55) -> 13.796362
B58: ='Historical Financial Statement'!B55 -> Receivables | C58: ='Historical Financial Statement'!C55 -> 12322 | D58: ='Historical Financial Statement'!D55 -> 13142 | E58: ='Historical Financial Statement'!E55 -> 14827 | F58: ='Historical Financial Statement'!F55 -> 18487 | G58: ='Historical Financial Statement'!G55 -> 19294 | H58: ='Historical Financial Statement'!H55 -> 22698 | I58: ='Historical Financial Statement'!I55 -> 25424 | ... L58: ='Historical Financial Statement'!L55 -> 35234 | M58: =(C60*M3)/365 -> 37083.325 | N58: =(D60*N3)/365 -> 41002.689 | O58: =(E60*O3)/365 -> 45202.889 | P58: =(F60*P3)/365 -> 50025.206 | Q58: =(G60*Q3)/365 -> 54689.824
B59: Days | C59: =365/(C3/C58) -> 65.672712 | D59: =365/(D3/D58) -> 68.018916 | E59: =365/(E3/E58) -> 65.459389 | F59: =365/(F3/F58) -> 74.321849 | G59: =365/(G3/G58) -> 70.092265 | H59: =365/(H3/H58) -> 68.108368 | I59: =365/(I3/I58) -> 63.227837 | J59: =365/(J3/J58) -> 71.715006 | ... Q59: =365/(Q3/Q58) -> 69.181412
B60: Average Days | C60: =AVERAGE(C59:L59) -> 68.837823 | D60: =AVERAGE(D59:M59) -> 69.154334 | E60: =AVERAGE(E59:N59) -> 69.267875 | F60: =AVERAGE(F59:O59) -> 69.648724 | G60: =AVERAGE(G59:P59) -> 69.181412
B62: ='Historical Financial Statement'!B50 -> Investments | C62: ='Historical Financial Statement'!C50 -> 16423 | D62: ='Historical Financial Statement'!D50 -> 12163 | E62: ='Historical Financial Statement'!E50 -> 11261 | F62: ='Historical Financial Statement'!F50 -> 8792 | G62: ='Historical Financial Statement'!G50 -> 14205 | H62: ='Historical Financial Statement'!H50 -> 20324 | I62: ='Historical Financial Statement'!I50 -> 19478 | ... L62: ='Historical Financial Statement'!L50 -> 21880 | M62: =M3*C64 -> 29762.378 | N62: =N3*D64 -> 30843.324 | O62: =O3*E64 -> 33233.679 | P62: =P3*F64 -> 36664.939 | Q62: =Q3*G64 -> 41595.806
B63: % Investments | C63: =C62/C3 -> 0.23980784 | D63: =D62/D3 -> 0.172471 | E63: =E62/E3 -> 0.13620804 | F63: =F62/F3 -> 0.096837792 | G63: =G62/G3 -> 0.14138267 | H63: =H62/H3 -> 0.16708182 | I63: =I62/I3 -> 0.13271376 | J63: =J62/J3 -> 0.16023297 | ... Q63: =Q62/Q3 -> 0.14415827
B64: Average % Investment | C64: =AVERAGE(C63:L63) -> 0.15136422 | D64: =AVERAGE(D63:M63) -> 0.14251986 | E64: =AVERAGE(E63:N63) -> 0.13952474 | F64: =AVERAGE(F63:O63) -> 0.13985641 | G64: =AVERAGE(G63:P63) -> 0.14415827
B66: ='Historical Financial Statement'!B49 -> Capital Work in Progress | C66: ='Historical Financial Statement'!C49 -> 1365 | D66: ='Historical Financial Statement'!D49 -> 1606 | E66: ='Historical Financial Statement'!E49 -> 1388 | F66: ='Historical Financial Statement'!F49 -> 954 | G66: ='Historical Financial Statement'!G49 -> 922 | H66: ='Historical Financial Statement'!H49 -> 416 | I66: ='Historical Financial Statement'!I49 -> 288 | ... L66: ='Historical Financial Statement'!L49 -> 526 | M66: =M18*C68 -> 1572.295 | N66: =N18*D68 -> 1402.9594 | O66: =O18*E68 -> 1123.5487 | P66: =P18*F68 -> 949.9876 | Q66: =Q18*G68 -> 918.26848
B67: % Capital Work in Progress | C67: =C66/C18 -> 0.09626913 | D67: =D66/D18 -> 0.12772387 | E67: =E66/E18 -> 0.088351369 | F67: =F66/F18 -> 0.040102568 | G67: =G66/G18 -> 0.036149775 | H67: =H66/H18 -> 0.016124031 | I67: =I66/I18 -> 0.0098545766 | J67: =J66/J18 -> 0.010607487 | ... Q67: =Q66/Q18 -> 0.026383859
B68: Average % Capital WP | C68: =AVERAGE(C67:L67) -> 0.046704991 | D68: =AVERAGE(D67:M67) -> 0.041748577 | E68: =AVERAGE(E67:N67) -> 0.033151047 | F68: =AVERAGE(F67:O67) -> 0.027631015 | G68: =AVERAGE(G67:P67) -> 0.026383859
B70: ='Historical Financial Statement'!B51 -> Other Assets | C70: ='Historical Financial Statement'!C51 -> 16234 | D70: ='Historical Financial Statement'!D51 -> 20046 | E70: ='Historical Financial Statement'!E51 -> 21312 | F70: ='Historical Financial Statement'!F51 -> 21129 | G70: ='Historical Financial Statement'!G51 -> 22871 | H70: ='Historical Financial Statement'!H51 -> 30019 | I70: ='Historical Financial Statement'!I51 -> 38008 | ... L70: ='Historical Financial Statement'!L51 -> 40677 | M70: =M3*C72 -> 48166.323 | N70: =N3*D72 -> 53184.578 | O70: =O3*E72 -> 57619.554 | P70: =P3*F72 -> 63001.592 | Q70: =Q3*G72 -> 69560.593
B71: % Other Assets | C71: =C70/C3 -> 0.23704807 | D71: =D70/D3 -> 0.28425172 | E71: =E70/E3 -> 0.25778047 | F71: =F70/F3 -> 0.2327213 | G71: =G70/G3 -> 0.22763556 | H71: =H70/H3 -> 0.24678357 | I71: =I70/I3 -> 0.2589683 | J71: =J70/J3 -> 0.25055639 | ... Q71: =Q70/Q3 -> 0.24107563
B72: Average % Other Assets | C72: =AVERAGE(C71:L71) -> 0.2449622 | D72: =AVERAGE(D71:M71) -> 0.24575362 | E72: =AVERAGE(E71:N71) -> 0.24190381 | F72: =AVERAGE(F71:O71) -> 0.24031614 | G72: =AVERAGE(G71:P71) -> 0.24107563

Sheet DCF Model
B1: ="DCF Model for "&'Data Sheet'!B1 -> DCF Model for INFOSYS LTD
B2: ="WACC Calculation for "&'Data Sheet'!B1 -> WACC Calculation for INFOSYS LTD | F2: ="Discount Cash-Flow for "&'Data Sheet'!B1 -> Discount Cash-Flow for INFOSYS LTD
B3: Equity | C3: 469200 | G3: 0 | H3: 1 | I3: 2 | J3: 3 | K3: 4 | L3: 5
B4: Debt | C4: 8525 | F4: EBIT | G4: ='Historical Financial Statement'!L14 -> 37378 | H4: ='Historical Financial Statement'!M14 -> 44799.589 | I4: ='Historical Financial Statement'!N14 -> 49300.176 | J4: ='Historical Financial Statement'!O14 -> 54363.77 | K4: ='Historical Financial Statement'!P14 -> 60339.398 | L4: ='Historical Financial Statement'!Q14 -> 66857.275
B5: Weightage of Equity | C5: =C3/SUM(C3:C4) -> 0.98215501 | F5: Depreciation | G5: ='Historical Financial Statement'!L13 -> 4902 | H5: ='Historical Financial Statement'!M13 -> 4711.642 | I5: ='Historical Financial Statement'!N13 -> 4763.7377 | J5: ='Historical Financial Statement'!O13 -> 4733.8014 | K5: ='Historical Financial Statement'!P13 -> 4813.7466 | L5: ='Historical Financial Statement'!Q13 -> 4946.5198
B6: Weightage of Debt | C6: =C4/(SUM(C3:C4)) -> 0.017844995 | F6: Cap-Ex | G6: =-'Historical Financial Statement'!L75 -> 2727 | H6: =-'Historical Financial Statement'!M75 -> 4606.0312 | I6: =-'Historical Financial Statement'!N75 -> 4704.311 | J6: =-'Historical Financial Statement'!O75 -> 5020.6413 | K6: =-'Historical Financial Statement'!P75 -> 5303.1497 | L6: =-'Historical Financial Statement'!Q75 -> 5369.4902
B7: Cost of Debt | C7: =('Historical Financial Statement'!L17/'DCF Model'!C4)*(1-'DCF Model'!C9) -> 0.035915073 | F7: Net Working Capital | G7: =SUM('Historical Financial Statement'!L55:L56)-'Historical Financial Statement'!L39 -> 30490 | H7: =SUM('Historical Financial Statement'!M55:M56)-'Historical Financial Statement'!M39 -> 32577.252 | I7: =SUM('Historical Financial Statement'!N55:N56)-'Historical Financial Statement'!N39 -> 35639.785 | J7: =SUM('Historical Financial Statement'!O55:O56)-'Historical Financial Statement'!O39 -> 38924.462 | K7: =SUM('Historical Financial Statement'!P55:P56)-'Historical Financial Statement'!P39 -> 42942.436 | L7: =SUM('Historical Financial Statement'!Q55:Q56)-'Historical Financial Statement'!Q39 -> 47024.871
B8: Cost Equity | C8: =C10+C12*(C11-C10) -> 0.10010161 | F8: ΔNet Working Capital | H8: =H7-G7 -> 2087.2522 | I8: =I7-H7 -> 3062.5326 | J8: =J7-I7 -> 3284.6777 | K8: =K7-J7 -> 4017.974 | L8: =L7-K7 -> 4082.4345
B9: Tax | C9: 0.264 | F9: FCFF | H9: =H4*(1-$C9)+H5-(H6+H8) -> 30990.856 | I9: =I4*(1-$C9)+I5-(I6+I8) -> 33281.823 | J9: =J4*(1-$C9)+J5-(J6+J8) -> 36440.217 | K9: =K4*(1-$C9)+K5-(K6+K8) -> 39902.42 | L9: =L4*(1-$C9)+L5-(L6+L8) -> 44701.549
B10: Fixed Market Return | C10: 0.0746
B11: Expected Market Return | C11: =_xlfn.RRI(10,'BETA Calculation'!F525,'BETA Calculation'!F4) -> 0.11215961 | F11: Perpetualty Growth Rate | H11: 0.06
B12: BETA(L) | C12: ='BETA Calculation'!J8 -> 0.67896364 | F12: WACC | H12: =C14 -> 0.098956203
F13: Ternimal Value | H13: =(L9*(1+H11))/(H12-H11) -> 1216331.1
B14: WACC | C14: =(C5*C8)+(C6*C7) -> 0.098956203
F15: Period | G15: FCFF | H15: Discount Factor | I15: PV(FCFF)
B16: India’s real GDP growth rate with Q1 FY 2026‑27 showing 7.8% growth | F16: =H3 -> 1 | G16: =H9 -> 30990.856 | H16: =1/(1+H$12)^F16 -> 0.90995437 | I16: =G16*H16 -> 28200.265
B17: India’s nominal GDP grew by 10.3% year‑on‑year in Q1 FY 2026‑27 | F17: =I3 -> 2 | G17: =I9 -> 33281.823 | H17: =1/(1+H$12)^F17 -> 0.82801696 | I17: =G17*H17 -> 27557.914
B18: India’s annual inflation rate stood at 4.96% (YoY) | F18: =J3 -> 3 | G18: =J9 -> 36440.217 | H18: =1/(1+H$12)^F18 -> 0.75345765 | I18: =G18*H18 -> 27456.161
F19: =K3 -> 4 | G19: =K9 -> 39902.42 | H19: =1/(1+H$12)^F19 -> 0.68561208 | I19: =G19*H19 -> 27357.581
F20: =L3 -> 5 | G20: =L9 -> 44701.549 | H20: =1/(1+H$12)^F20 -> 0.62387571 | I20: =G20*H20 -> 27888.211
G21: =H13 -> 1216331.1 | I21: =G21*H20 -> 758839.45
I22: =SUM(I16:I21) -> 897299.58
F25: Intrinsic Value | G25: =I22 -> 897299.58
F26: Net Debt | G26: ='COMP Analysis'!F4 -> -13025
F27: Market Captalization | G27: =G25-G26 -> 910324.58
F28: No. of Shares | G28: ='Data Sheet'!K93 -> 405.56
F29: Price Per Share | G29: =G27/G28 -> 2244.6114
E31: Price Per Share | F31: > | G31: Market Price Per Share
F33: Shares are Undervalued | H33: BUY

Sheet COMP Analysis
B1: ="COMP Analysis for "&'Data Sheet'!B1 -> COMP Analysis for INFOSYS LTD
C2: Market | I2: Finance | N2: Valuation
B3: Company Name | C3: Share Price | D3: Shares Outstanding | E3: Market Cap | F3: Net Debt | G3: Enterprise Value | I3: Revenue | J3: EBITDA | K3: EBIT | L3: Net Profit | N3: EV/Revenue | O3: EV/EBITDA | P3: EV/EBIT | Q3: P/E
B4: Infosys | C4: 1154 | D4: =E4/C4 -> 406.58579 | E4: 469200 | F4: ='Historical Financial Statement'!L34-'Historical Financial Statement'!L57 -> -13025 | G4: =E4+F4 -> 456175 | I4: ='Historical Financial Statement'!L3 -> 178650 | J4: ='Historical Financial Statement'!L10 -> 42280 | K4: ='Historical Financial Statement'!L14 -> 37378 | L4: ='Historical Financial Statement'!L23 -> 29474 | N4: =$G4/I4 -> 2.5534565 | O4: =$G4/J4 -> 10.78938 | P4: =$G4/K4 -> 12.204372 | Q4: =E4/L4 -> 15.919115
B5: TCS | C5: 2528 | D5: =E5/C5 -> 362.37263 | E5: 916078 | F5: =11283-12950 -> -1667 | G5: =E5+F5 -> 914411 | I5: 267021 | J5: =72398+5560 -> 77958 | K5: 72398 | L5: 49454 | N5: =$G5/I5 -> 3.424491 | O5: =$G5/J5 -> 11.729534 | P5: =$G5/K5 -> 12.630335 | Q5: =E5/L5 -> 18.52384
B6: HCL Technologies | C6: 1424 | D6: =E6/C6 -> 270.54846 | E6: 385261 | F6: =5215-23425 -> -18210 | G6: =E6+F6 -> 367051 | I6: 130144 | J6: =26752+4355 -> 31107 | K6: 26752 | L6: 16652 | N6: =$G6/I6 -> 2.8203452 | O6: =$G6/J6 -> 11.799627 | P6: =$G6/K6 -> 13.720507 | Q6: =E6/L6 -> 23.13602
B7: Wipro | C7: 190 | D7: =E7/C7 -> 991.37368 | E7: 188361 | F7: =20291-10556 -> 9735 | G7: =E7+F7 -> 198096 | I7: =92624 -> 92624 | J7: =17811+2911 -> 20722 | K7: 17811 | L7: 13266 | N7: =$G7/I7 -> 2.1387113 | O7: =$G7/J7 -> 9.559695 | P7: =$G7/K7 -> 11.122116 | Q7: =E7/L7 -> 14.198779
B8: Tech Mahindra | C8: 1789 | D8: =E8/C8 -> 98.262717 | E8: 175792 | F8: =2186-5105 -> -2919 | G8: =E8+F8 -> 172873 | I8: 56815 | J8: =9033+1882 -> 10915 | K8: 9033 | L8: 4806 | N8: =$G8/I8 -> 3.0427352 | O8: =$G8/J8 -> 15.838113 | P8: =$G8/K8 -> 19.137939 | Q8: =E8/L8 -> 36.577611
B10: Max | N10: =MAX(N4:N8) -> 3.424491 | O10: =MAX(O4:O8) -> 15.838113 | P10: =MAX(P4:P8) -> 19.137939 | Q10: =MAX(Q4:Q8) -> 36.577611
B11: 75th Percentile | N11: =_xlfn.PERCENTILE.EXC(N4:N8,0.75) -> 3.2336131 | O11: =_xlfn.PERCENTILE.EXC(O4:O8,0.75) -> 13.81887 | P11: =_xlfn.PERCENTILE.EXC(P4:P8,0.75) -> 16.429223 | Q11: =_xlfn.PERCENTILE.EXC(Q4:Q8,0.75) -> 29.856816
B12: Median | N12: =MEDIAN(N4:N8) -> 2.8203452 | O12: =MEDIAN(O4:O8) -> 11.729534 | P12: =MEDIAN(P4:P8) -> 12.630335 | Q12: =MEDIAN(Q4:Q8) -> 18.52384
B13: Average | N13: =AVERAGE(N4:N8) -> 2.7959478 | O13: =AVERAGE(O4:O8) -> 11.94327 | P13: =AVERAGE(P4:P8) -> 13.763054 | Q13: =AVERAGE(Q4:Q8) -> 21.671073
B14: 25th Percentile | N14: =_xlfn.PERCENTILE.EXC(N4:N8,0.25) -> 2.3460839 | O14: =_xlfn.PERCENTILE.EXC(O4:O8,0.25) -> 10.174538 | P14: =_xlfn.PERCENTILE.EXC(P4:P8,0.25) -> 11.663244 | Q14: =_xlfn.PERCENTILE.EXC(Q4:Q8,0.25) -> 15.058947
B15: Min | N15: =MIN(N4:N8) -> 2.1387113 | O15: =MIN(O4:O8) -> 9.559695 | P15: =MIN(P4:P8) -> 11.122116 | Q15: =MIN(Q4:Q8) -> 14.198779
N17: Valuation
B18: ='Data Sheet'!B1 -> INFOSYS LTD | N18: EV/Revenue | O18: EV/EBITDA | P18: EV/EBIT | Q18: P/E
B19: Implied Enterprise Value | N19: =N13*I4 -> 499496.08 | O19: =O13*J4 -> 504961.45 | P19: =P13*K4 -> 514435.42 | Q19: =Q21+Q20 -> 625708.21
B20: Net Debt | N20: =$F4 -> -13025 | O20: =$F4 -> -13025 | P20: =$F4 -> -13025 | Q20: =$F4 -> -13025
B21: Implied Market Value | N21: =N19-N20 -> 512521.08 | O21: =O19-O20 -> 517986.45 | P21: =P19-P20 -> 527460.42 | Q21: =Q13*L4 -> 638733.21
B22: Shares Outstanding | N22: =$D4 -> 406.58579 | O22: =$D4 -> 406.58579 | P22: =$D4 -> 406.58579 | Q22: =$D4 -> 406.58579
B23: Implied Value Per Share | N23: =N21/N22 -> 1260.5484 | O23: =O21/O22 -> 1273.9905 | P23: =P21/P22 -> 1297.2918 | Q23: =Q21/Q22 -> 1570.9679
E25: Share Price | F25: < | G25: All Implied Value Per Share
E27: Shares are Undervalued | H27: BUY

Sheet Common Size Statement
B1: ="Common Size Income Statement for "&'Data Sheet'!B1 -> Common Size Income Statement for INFOSYS LTD | N1: ="Common Size Balance Sheet for "&'Data Sheet'!B1 -> Common Size Balance Sheet for INFOSYS LTD
B2: ='Data Sheet'!A16 -> Report Date | C2: ='Data Sheet'!B16 -> 42825 | D2: ='Data Sheet'!C16 -> 43190 | E2: ='Data Sheet'!D16 -> 43555 | F2: ='Data Sheet'!E16 -> 43921 | G2: ='Data Sheet'!F16 -> 44286 | H2: ='Data Sheet'!G16 -> 44651 | I2: ='Data Sheet'!H16 -> 45016 | ... L2: ='Data Sheet'!K16 -> 46112 | N2: ='Historical Financial Statement'!B2 -> Report Date | O2: ='Historical Financial Statement'!C2 -> 42825 | P2: ='Historical Financial Statement'!D2 -> 43190 | Q2: ='Historical Financial Statement'!E2 -> 43555 | R2: ='Historical Financial Statement'!F2 -> 43921 | S2: ='Historical Financial Statement'!G2 -> 44286 | T2: ='Historical Financial Statement'!H2 -> 44651 | U2: ='Historical Financial Statement'!I2 -> 45016 | ... X2: ='Historical Financial Statement'!L2 -> 46112
B3: ='Data Sheet'!A17 -> Sales | C3: ='Data Sheet'!B17/'Data Sheet'!B$17 -> 1 | D3: ='Data Sheet'!C17/'Data Sheet'!C$17 -> 1 | E3: ='Data Sheet'!D17/'Data Sheet'!D$17 -> 1 | F3: ='Data Sheet'!E17/'Data Sheet'!E$17 -> 1 | G3: ='Data Sheet'!F17/'Data Sheet'!F$17 -> 1 | H3: ='Data Sheet'!G17/'Data Sheet'!G$17 -> 1 | I3: ='Data Sheet'!H17/'Data Sheet'!H$17 -> 1 | J3: ='Data Sheet'!I17/'Data Sheet'!I$17 -> 1 | ... L3: ='Data Sheet'!K17/'Data Sheet'!K$17 -> 1 | N3: ='Data Sheet'!A57 -> Equity Share Capital | O3: ='Data Sheet'!B57/'Data Sheet'!B$61 -> 0.013758599 | P3: ='Data Sheet'!C57/'Data Sheet'!C$61 -> 0.013711578 | Q3: ='Data Sheet'!D57/'Data Sheet'!D$61 -> 0.025813052 | R3: ='Data Sheet'!E57/'Data Sheet'!E$61 -> 0.023115468 | S3: ='Data Sheet'!F57/'Data Sheet'!F$61 -> 0.019756118 | T3: ='Data Sheet'!G57/'Data Sheet'!G$61 -> 0.017973254 | U3: ='Data Sheet'!H57/'Data Sheet'!H$61 -> 0.01660567 | V3: ='Data Sheet'!I57/'Data Sheet'!I$61 -> 0.015225702 | ... X3: ='Data Sheet'!K57/'Data Sheet'!K$61 -> 0.013118324
B4: ='Data Sheet'!A18 -> Raw Material Cost | C4: ='Data Sheet'!B18/'Data Sheet'!B$17 -> 0 | D4: ='Data Sheet'!C18/'Data Sheet'!C$17 -> 0 | E4: ='Data Sheet'!D18/'Data Sheet'!D$17 -> 0 | F4: ='Data Sheet'!E18/'Data Sheet'!E$17 -> 0 | G4: ='Data Sheet'!F18/'Data Sheet'!F$17 -> 0 | H4: ='Data Sheet'!G18/'Data Sheet'!G$17 -> 0 | I4: ='Data Sheet'!H18/'Data Sheet'!H$17 -> 0 | J4: ='Data Sheet'!I18/'Data Sheet'!I$17 -> 0 | ... L4: ='Data Sheet'!K18/'Data Sheet'!K$17 -> 0 | N4: ='Data Sheet'!A58 -> Reserves | O4: ='Data Sheet'!B58/'Data Sheet'!B$61 -> 0.8158705 | P4: ='Data Sheet'!C58/'Data Sheet'!C$61 -> 0.80448399 | Q4: ='Data Sheet'!D58/'Data Sheet'!D$61 -> 0.74677039 | R4: ='Data Sheet'!E58/'Data Sheet'!E$61 -> 0.68984749 | S4: ='Data Sheet'!F58/'Data Sheet'!F$61 -> 0.69041307 | T4: ='Data Sheet'!G58/'Data Sheet'!G$61 -> 0.627539 | U4: ='Data Sheet'!H58/'Data Sheet'!H$61 -> 0.58860638 | V4: ='Data Sheet'!I58/'Data Sheet'!I$61 -> 0.6325908 | ... X4: ='Data Sheet'!K58/'Data Sheet'!K$61 -> 0.58869128
B5: ='Data Sheet'!A19 -> Change in Inventory | C5: ='Data Sheet'!B19/'Data Sheet'!B$17 -> 0 | D5: ='Data Sheet'!C19/'Data Sheet'!C$17 -> 0 | E5: ='Data Sheet'!D19/'Data Sheet'!D$17 -> 0 | F5: ='Data Sheet'!E19/'Data Sheet'!E$17 -> 0 | G5: ='Data Sheet'!F19/'Data Sheet'!F$17 -> 0 | H5: ='Data Sheet'!G19/'Data Sheet'!G$17 -> 0 | I5: ='Data Sheet'!H19/'Data Sheet'!H$17 -> 0 | J5: ='Data Sheet'!I19/'Data Sheet'!I$17 -> 0 | ... L5: ='Data Sheet'!K19/'Data Sheet'!K$17 -> 0 | N5: ='Data Sheet'!A59 -> Borrowings | O5: ='Data Sheet'!B59/'Data Sheet'!B$61 -> 0 | P5: ='Data Sheet'!C59/'Data Sheet'!C$61 -> 0 | Q5: ='Data Sheet'!D59/'Data Sheet'!D$61 -> 0 | R5: ='Data Sheet'!E59/'Data Sheet'!E$61 -> 0.05046841 | S5: ='Data Sheet'!F59/'Data Sheet'!F$61 -> 0.049529816 | T5: ='Data Sheet'!G59/'Data Sheet'!G$61 -> 0.046894945 | U5: ='Data Sheet'!H59/'Data Sheet'!H$61 -> 0.066607275 | V5: ='Data Sheet'!I59/'Data Sheet'!I$61 -> 0.061454198 | ... X5: ='Data Sheet'!K59/'Data Sheet'!K$61 -> 0.059473193
B6: ='Data Sheet'!A20 -> Power and Fuel | C6: ='Data Sheet'!B20/'Data Sheet'!B$17 -> 0.0033292448 | D6: ='Data Sheet'!C20/'Data Sheet'!C$17 -> 0.0029352542 | E6: ='Data Sheet'!D20/'Data Sheet'!D$17 -> 0.0026731176 | F6: ='Data Sheet'!E20/'Data Sheet'!E$17 -> 0.0025222764 | G6: ='Data Sheet'!F20/'Data Sheet'!F$17 -> 0.0014232821 | H6: ='Data Sheet'!G20/'Data Sheet'!G$17 -> 0.0010851604 | I6: ='Data Sheet'!H20/'Data Sheet'!H$17 -> 0.0011991797 | J6: ='Data Sheet'!I20/'Data Sheet'!I$17 -> 0.0012949828 | ... L6: ='Data Sheet'!K20/'Data Sheet'!K$17 -> 0.0012482508 | N6: ='Data Sheet'!A60 -> Other Liabilities | O6: ='Data Sheet'!B60/'Data Sheet'!B$61 -> 0.1703709 | P6: ='Data Sheet'!C60/'Data Sheet'!C$61 -> 0.18180443 | Q6: ='Data Sheet'!D60/'Data Sheet'!D$61 -> 0.22741655 | R6: ='Data Sheet'!E60/'Data Sheet'!E$61 -> 0.23656863 | S6: ='Data Sheet'!F60/'Data Sheet'!F$61 -> 0.24030099 | T6: ='Data Sheet'!G60/'Data Sheet'!G$61 -> 0.3075928 | U6: ='Data Sheet'!H60/'Data Sheet'!H$61 -> 0.32818068 | V6: ='Data Sheet'!I60/'Data Sheet'!I$61 -> 0.2907293 | ... X6: ='Data Sheet'!K60/'Data Sheet'!K$61 -> 0.3387172
B7: ='Data Sheet'!A21 -> Other Mfr. Exp | C7: ='Data Sheet'!B21/'Data Sheet'!B$17 -> 0.098008294 | D7: ='Data Sheet'!C21/'Data Sheet'!C$17 -> 0.10331528 | E7: ='Data Sheet'!D21/'Data Sheet'!D$17 -> 0.11977018 | F7: ='Data Sheet'!E21/'Data Sheet'!E$17 -> 0.12210461 | G7: ='Data Sheet'!F21/'Data Sheet'!F$17 -> 0.12739868 | H7: ='Data Sheet'!G21/'Data Sheet'!G$17 -> 0.17009068 | I7: ='Data Sheet'!H21/'Data Sheet'!H$17 -> 0.1794 | J7: ='Data Sheet'!I21/'Data Sheet'!I$17 -> 0.17697013 | ... L7: ='Data Sheet'!K21/'Data Sheet'!K$17 -> 0.18428212 | N7: ='Data Sheet'!A61&" Liabilities" -> Total Liabilities | O7: ='Data Sheet'!B61/'Data Sheet'!B$61 -> 1 | P7: ='Data Sheet'!C61/'Data Sheet'!C$61 -> 1 | Q7: ='Data Sheet'!D61/'Data Sheet'!D$61 -> 1 | R7: ='Data Sheet'!E61/'Data Sheet'!E$61 -> 1 | S7: ='Data Sheet'!F61/'Data Sheet'!F$61 -> 1 | T7: ='Data Sheet'!G61/'Data Sheet'!G$61 -> 1 | U7: ='Data Sheet'!H61/'Data Sheet'!H$61 -> 1 | V7: ='Data Sheet'!I61/'Data Sheet'!I$61 -> 1 | ... X7: ='Data Sheet'!K61/'Data Sheet'!K$61 -> 1
B8: ='Data Sheet'!A22 -> Employee Cost | C8: ='Data Sheet'!B22/'Data Sheet'!B$17 -> 0.55004089 | D8: ='Data Sheet'!C22/'Data Sheet'!C$17 -> 0.55162928 | E8: ='Data Sheet'!D22/'Data Sheet'!D$17 -> 0.54820683 | F8: ='Data Sheet'!E22/'Data Sheet'!E$17 -> 0.56057318 | G8: ='Data Sheet'!F22/'Data Sheet'!F$17 -> 0.5528605 | H8: ='Data Sheet'!G22/'Data Sheet'!G$17 -> 0.52611373 | I8: ='Data Sheet'!H22/'Data Sheet'!H$17 -> 0.53400288 | J8: ='Data Sheet'!I22/'Data Sheet'!I$17 -> 0.53774972 | ... L8: ='Data Sheet'!K22/'Data Sheet'!K$17 -> 0.53239295
B9: ='Data Sheet'!A23 -> Selling and admin | C9: ='Data Sheet'!B23/'Data Sheet'!B$17 -> 0.066935343 | D9: ='Data Sheet'!C23/'Data Sheet'!C$17 -> 0.065015173 | E9: ='Data Sheet'!D23/'Data Sheet'!D$17 -> 0.067166616 | F9: ='Data Sheet'!E23/'Data Sheet'!E$17 -> 0.059201903 | G9: ='Data Sheet'!F23/'Data Sheet'!F$17 -> 0.031789951 | H9: ='Data Sheet'!G23/'Data Sheet'!G$17 -> 0.035391028 | I9: ='Data Sheet'!H23/'Data Sheet'!H$17 -> 0.03611166 | J9: ='Data Sheet'!I23/'Data Sheet'!I$17 -> 0.037125008 | ... L9: ='Data Sheet'!K23/'Data Sheet'!K$17 -> 0.037973692 | N9: ='Data Sheet'!A62 -> Net Block | O9: ='Data Sheet'!B62/'Data Sheet'!B$66 -> 0.17052725 | P9: ='Data Sheet'!C62/'Data Sheet'!C$66 -> 0.1584645 | Q9: ='Data Sheet'!D62/'Data Sheet'!D$66 -> 0.18687698 | R9: ='Data Sheet'!E62/'Data Sheet'!E$66 -> 0.25913943 | S9: ='Data Sheet'!F62/'Data Sheet'!F$66 -> 0.23723154 | T9: ='Data Sheet'!G62/'Data Sheet'!G$66 -> 0.22102477 | U9: ='Data Sheet'!H62/'Data Sheet'!H$66 -> 0.23455809 | V9: ='Data Sheet'!I62/'Data Sheet'!I$66 -> 0.20307308 | ... X9: ='Data Sheet'!K62/'Data Sheet'!K$66 -> 0.21887639
B10: ='Data Sheet'!A24 -> Other Expenses | C10: ='Data Sheet'!B24/'Data Sheet'!B$17 -> 0.01003154 | D10: ='Data Sheet'!C24/'Data Sheet'!C$17 -> 0.01020958 | E10: ='Data Sheet'!D24/'Data Sheet'!D$17 -> 0.018215906 | F10: ='Data Sheet'!E24/'Data Sheet'!E$17 -> 0.010342435 | G10: ='Data Sheet'!F24/'Data Sheet'!F$17 -> 0.0089477665 | H10: ='Data Sheet'!G24/'Data Sheet'!G$17 -> 0.0084346561 | I10: ='Data Sheet'!H24/'Data Sheet'!H$17 -> 0.0099272997 | J10: ='Data Sheet'!I24/'Data Sheet'!I$17 -> 0.0098262511 | ... L10: ='Data Sheet'!K24/'Data Sheet'!K$17 -> 0.0074391268 | N10: ='Data Sheet'!A63 -> Capital Work in Progress | O10: ='Data Sheet'!B63/'Data Sheet'!B$66 -> 0.01641651 | P10: ='Data Sheet'!C63/'Data Sheet'!C$66 -> 0.020239701 | Q10: ='Data Sheet'!D63/'Data Sheet'!D$66 -> 0.016510837 | R10: ='Data Sheet'!E63/'Data Sheet'!E$66 -> 0.010392157 | S10: ='Data Sheet'!F63/'Data Sheet'!F$66 -> 0.0085758667 | T10: ='Data Sheet'!G63/'Data Sheet'!G$66 -> 0.0035638102 | U10: ='Data Sheet'!H63/'Data Sheet'!H$66 -> 0.0023114707 | V10: ='Data Sheet'!I63/'Data Sheet'!I$66 -> 0.002154095 | ... X10: ='Data Sheet'!K63/'Data Sheet'!K$66 -> 0.0034092088
B11: ='Data Sheet'!A25 -> Other Income | C11: ='Data Sheet'!B25/'Data Sheet'!B$17 -> 0.04453595 | D11: ='Data Sheet'!C25/'Data Sheet'!C$17 -> 0.046949888 | E11: ='Data Sheet'!D25/'Data Sheet'!D$17 -> 0.034859389 | F11: ='Data Sheet'!E25/'Data Sheet'!E$17 -> 0.030873104 | G11: ='Data Sheet'!F25/'Data Sheet'!F$17 -> 0.021906601 | H11: ='Data Sheet'!G25/'Data Sheet'!G$17 -> 0.018866994 | I11: ='Data Sheet'!H25/'Data Sheet'!H$17 -> 0.01840332 | J11: ='Data Sheet'!I25/'Data Sheet'!I$17 -> 0.030656602 | ... L11: ='Data Sheet'!K25/'Data Sheet'!K$17 -> 0.01697733 | N11: ='Data Sheet'!A64 -> Investments | O11: ='Data Sheet'!B64/'Data Sheet'!B$66 -> 0.19751527 | P11: ='Data Sheet'!C64/'Data Sheet'!C$66 -> 0.15328486 | Q11: ='Data Sheet'!D64/'Data Sheet'!D$66 -> 0.13395427 | R11: ='Data Sheet'!E64/'Data Sheet'!E$66 -> 0.09577342 | S11: ='Data Sheet'!F64/'Data Sheet'!F$66 -> 0.13212602 | T11: ='Data Sheet'!G64/'Data Sheet'!G$66 -> 0.17411269 | U11: ='Data Sheet'!H64/'Data Sheet'!H$66 -> 0.15632926 | V11: ='Data Sheet'!I64/'Data Sheet'!I$66 -> 0.18102485 | ... X11: ='Data Sheet'!K64/'Data Sheet'!K$66 -> 0.14181271
B12: ='Data Sheet'!A26 -> Depreciation | C12: ='Data Sheet'!B26/'Data Sheet'!B$17 -> 0.024867122 | D12: ='Data Sheet'!C26/'Data Sheet'!C$17 -> 0.026417288 | E12: ='Data Sheet'!D26/'Data Sheet'!D$17 -> 0.024324161 | F12: ='Data Sheet'!E26/'Data Sheet'!E$17 -> 0.031864392 | G12: ='Data Sheet'!F26/'Data Sheet'!F$17 -> 0.032516522 | H12: ='Data Sheet'!G26/'Data Sheet'!G$17 -> 0.028575891 | I12: ='Data Sheet'!H26/'Data Sheet'!H$17 -> 0.028787125 | J12: ='Data Sheet'!I26/'Data Sheet'!I$17 -> 0.030441856 | ... L12: ='Data Sheet'!K26/'Data Sheet'!K$17 -> 0.027439127 | N12: ='Data Sheet'!A74 -> Other Assets | O12: ='Data Sheet'!B74/'Data Sheet'!B$66 -> 0.19524222 | P12: ='Data Sheet'!C74/'Data Sheet'!C$66 -> 0.25263078 | Q12: ='Data Sheet'!D74/'Data Sheet'!D$66 -> 0.2535151 | R12: ='Data Sheet'!E74/'Data Sheet'!E$66 -> 0.2301634 | S12: ='Data Sheet'!F74/'Data Sheet'!F$66 -> 0.21273172 | T12: ='Data Sheet'!G74/'Data Sheet'!G$66 -> 0.25716831 | U12: ='Data Sheet'!H74/'Data Sheet'!H$66 -> 0.30504992 | V12: ='Data Sheet'!I74/'Data Sheet'!I$66 -> 0.28306867 | ... X12: ='Data Sheet'!K74/'Data Sheet'!K$66 -> 0.26364332
B13: ='Data Sheet'!A27 -> Interest | C13: ='Data Sheet'!B27/'Data Sheet'!B$17 -> 0 | D13: ='Data Sheet'!C27/'Data Sheet'!C$17 -> 0 | E13: ='Data Sheet'!D27/'Data Sheet'!D$17 -> 0 | F13: ='Data Sheet'!E27/'Data Sheet'!E$17 -> 0.0018724323 | G13: ='Data Sheet'!F27/'Data Sheet'!F$17 -> 0.0019408392 | H13: ='Data Sheet'!G27/'Data Sheet'!G$17 -> 0.0016441825 | I13: ='Data Sheet'!H27/'Data Sheet'!H$17 -> 0.0019350399 | J13: ='Data Sheet'!I27/'Data Sheet'!I$17 -> 0.003058502 | ... L13: ='Data Sheet'!K27/'Data Sheet'!K$17 -> 0.0023285754 | N13: ='Data Sheet'!A67 -> Receivables | O13: ='Data Sheet'!B67/'Data Sheet'!B$66 -> 0.14819358 | P13: ='Data Sheet'!C67/'Data Sheet'!C$66 -> 0.16562276 | Q13: ='Data Sheet'!D67/'Data Sheet'!D$66 -> 0.17637333 | R13: ='Data Sheet'!E67/'Data Sheet'!E$66 -> 0.20138344 | S13: ='Data Sheet'!F67/'Data Sheet'!F$66 -> 0.17946071 | T13: ='Data Sheet'!G67/'Data Sheet'!G$66 -> 0.19445039 | U13: ='Data Sheet'!H67/'Data Sheet'!H$66 -> 0.20405149 | V13: ='Data Sheet'!I67/'Data Sheet'!I$66 -> 0.22197471 | ... X13: ='Data Sheet'!K67/'Data Sheet'!K$66 -> 0.22836514
B14: ='Data Sheet'!A28 -> Profit before tax | C14: ='Data Sheet'!B28/'Data Sheet'!B$17 -> 0.29132352 | D14: ='Data Sheet'!C28/'Data Sheet'!C$17 -> 0.28742804 | E14: ='Data Sheet'!D28/'Data Sheet'!D$17 -> 0.25450257 | F14: ='Data Sheet'!E28/'Data Sheet'!E$17 -> 0.24239187 | G14: ='Data Sheet'!F28/'Data Sheet'!F$17 -> 0.26502906 | H14: ='Data Sheet'!G28/'Data Sheet'!G$17 -> 0.24753167 | I14: ='Data Sheet'!H28/'Data Sheet'!H$17 -> 0.22704014 | J14: ='Data Sheet'!I28/'Data Sheet'!I$17 -> 0.23419015 | ... L14: ='Data Sheet'!K28/'Data Sheet'!K$17 -> 0.2238735 | N14: ='Data Sheet'!A68 -> Inventory | O14: ='Data Sheet'!B68/'Data Sheet'!B$66 -> 0 | P14: ='Data Sheet'!C68/'Data Sheet'!C$66 -> 0 | Q14: ='Data Sheet'!D68/'Data Sheet'!D$66 -> 0 | R14: ='Data Sheet'!E68/'Data Sheet'!E$66 -> 0 | S14: ='Data Sheet'!F68/'Data Sheet'!F$66 -> 0 | T14: ='Data Sheet'!G68/'Data Sheet'!G$66 -> 0 | U14: ='Data Sheet'!H68/'Data Sheet'!H$66 -> 0 | V14: ='Data Sheet'!I68/'Data Sheet'!I$66 -> 0 | ... X14: ='Data Sheet'!K68/'Data Sheet'!K$66 -> 0
B15: ='Data Sheet'!A29 -> Tax | C15: ='Data Sheet'!B29/'Data Sheet'!B$17 -> 0.081741721 | D15: ='Data Sheet'!C29/'Data Sheet'!C$17 -> 0.060137262 | E15: ='Data Sheet'!D29/'Data Sheet'!D$17 -> 0.06811007 | F15: ='Data Sheet'!E29/'Data Sheet'!E$17 -> 0.059124803 | G15: ='Data Sheet'!F29/'Data Sheet'!F$17 -> 0.071711522 | H15: ='Data Sheet'!G29/'Data Sheet'!G$17 -> 0.065471346 | I15: ='Data Sheet'!H29/'Data Sheet'!H$17 -> 0.06277978 | J15: ='Data Sheet'!I29/'Data Sheet'!I$17 -> 0.063382573 | ... L15: ='Data Sheet'!K29/'Data Sheet'!K$17 -> 0.058891688 | N15: ='Data Sheet'!A69 -> Cash & Bank | O15: ='Data Sheet'!B69/'Data Sheet'!B$66 -> 0.27210516 | P15: ='Data Sheet'!C69/'Data Sheet'!C$66 -> 0.2497574 | Q15: ='Data Sheet'!D69/'Data Sheet'!D$66 -> 0.23276949 | R15: ='Data Sheet'!E69/'Data Sheet'!E$66 -> 0.20314815 | S15: ='Data Sheet'!F69/'Data Sheet'!F$66 -> 0.22987415 | T15: ='Data Sheet'!G69/'Data Sheet'!G$66 -> 0.14968003 | U15: ='Data Sheet'!H69/'Data Sheet'!H$66 -> 0.097699766 | V15: ='Data Sheet'!I69/'Data Sheet'!I$66 -> 0.1087046 | ... X15: ='Data Sheet'!K69/'Data Sheet'!K$66 -> 0.14389324
B16: ='Data Sheet'!A30 -> Net profit | C16: ='Data Sheet'!B30/'Data Sheet'!B$17 -> 0.2095818 | D16: ='Data Sheet'!C30/'Data Sheet'!C$17 -> 0.22729077 | E16: ='Data Sheet'!D30/'Data Sheet'!D$17 -> 0.18631993 | F16: ='Data Sheet'!E30/'Data Sheet'!E$17 -> 0.18277142 | G16: ='Data Sheet'!F30/'Data Sheet'!F$17 -> 0.19260092 | H16: ='Data Sheet'!G30/'Data Sheet'!G$17 -> 0.18176437 | I16: ='Data Sheet'!H30/'Data Sheet'!H$17 -> 0.16417178 | J16: ='Data Sheet'!I30/'Data Sheet'!I$17 -> 0.17070996 | ... L16: ='Data Sheet'!K30/'Data Sheet'!K$17 -> 0.16479149 | N16: ='Data Sheet'!A66&" Assets" -> Total Assets | O16: ='Data Sheet'!B66/'Data Sheet'!B$66 -> 1 | P16: ='Data Sheet'!C66/'Data Sheet'!C$66 -> 1 | Q16: ='Data Sheet'!D66/'Data Sheet'!D$66 -> 1 | R16: ='Data Sheet'!E66/'Data Sheet'!E$66 -> 1 | S16: ='Data Sheet'!F66/'Data Sheet'!F$66 -> 1 | T16: ='Data Sheet'!G66/'Data Sheet'!G$66 -> 1 | U16: ='Data Sheet'!H66/'Data Sheet'!H$66 -> 1 | V16: ='Data Sheet'!I66/'Data Sheet'!I$66 -> 1 | ... X16: ='Data Sheet'!K66/'Data Sheet'!K$66 -> 1
B17: ='Data Sheet'!A31 -> Dividend Amount | C17: ='Data Sheet'!B31/'Data Sheet'!B$17 -> 0.086028853 | D17: ='Data Sheet'!C31/'Data Sheet'!C$17 -> 0.13422194 | E17: ='Data Sheet'!D31/'Data Sheet'!D$17 -> 0.11155125 | F17: ='Data Sheet'!E31/'Data Sheet'!E$17 -> 0.081803262 | G17: ='Data Sheet'!F31/'Data Sheet'!F$17 -> 0.11415718 | H17: ='Data Sheet'!G31/'Data Sheet'!G$17 -> 0.10693434 | I17: ='Data Sheet'!H31/'Data Sheet'!H$17 -> 0.095860786 | J17: ='Data Sheet'!I31/'Data Sheet'!I$17 -> 0.12398777 | ... L17: ='Data Sheet'!K31/'Data Sheet'!K$17 -> 0.10876238
B18: ='Data Sheet'!A32 -> EBITDA | C18: ='Data Sheet'!B32/'Data Sheet'!B$17 -> 0.27165469 | D18: ='Data Sheet'!C32/'Data Sheet'!C$17 -> 0.26689544 | E18: ='Data Sheet'!D32/'Data Sheet'!D$17 -> 0.24396734 | F18: ='Data Sheet'!E32/'Data Sheet'!E$17 -> 0.24525559 | G18: ='Data Sheet'!F32/'Data Sheet'!F$17 -> 0.27757982 | H18: ='Data Sheet'!G32/'Data Sheet'!G$17 -> 0.25888475 | I18: ='Data Sheet'!H32/'Data Sheet'!H$17 -> 0.23935898 | J18: ='Data Sheet'!I32/'Data Sheet'!I$17 -> 0.2370339 | ... L18: ='Data Sheet'!K32/'Data Sheet'!K$17 -> 0.23666387
B19: ='Data Sheet'!A33 -> EBIT | C19: ='Data Sheet'!B33/'Data Sheet'!B$17 -> 0.24678757 | D19: ='Data Sheet'!C33/'Data Sheet'!C$17 -> 0.24047815 | E19: ='Data Sheet'!D33/'Data Sheet'!D$17 -> 0.21964318 | F19: ='Data Sheet'!E33/'Data Sheet'!E$17 -> 0.2133912 | G19: ='Data Sheet'!F33/'Data Sheet'!F$17 -> 0.2450633 | H19: ='Data Sheet'!G33/'Data Sheet'!G$17 -> 0.23030886 | I19: ='Data Sheet'!H33/'Data Sheet'!H$17 -> 0.21057186 | J19: ='Data Sheet'!I33/'Data Sheet'!I$17 -> 0.20659205 | ... L19: ='Data Sheet'!K33/'Data Sheet'!K$17 -> 0.20922474

Sheet Manual Data
C2: 42795 | D2: 43160 | E2: 43525 | F2: 43891 | G2: 44256 | H2: 44621 | I2: 44986 | J2: 45352 | K2: 45717 | L2: 46082
B3: Cash from Operating Activity
B4: Profit from operations | C4: 19340 | D4: 19963 | E4: 22126 | F4: 23920 | G4: 28845 | H4: 32921 | I4: 37605 | J4: 39523 | K4: 41591 | L4: 45273
B5: Receivables | C5: -1743 | D5: -1523 | E5: -2881 | F5: -3861 | G5: -1835 | H5: -7937 | I5: -7076 | J5: -2667 | K5: -1769 | L5: -5177
B6: Payables | C6: -19 | D6: 328 | E6: 916 | F6: -373 | G6: -245 | H6: 1489 | I6: -279 | J6: 91 | K6: 176 | L6: -26
B7: Loans Advances | C7: 0 | D7: 0 | E7: 0 | F7: 0 | G7: -534 | H7: -1914 | I7: -3108 | J7: -1172 | K7: -1024 | L7: -2645
B8: Other WC items | C8: -394 | D8: 1279 | E8: 1512 | F8: 1867 | G8: 3382 | H8: 6938 | I8: 4119 | J8: -1334 | K8: 2322 | L8: 5209
B9: Working capital changes | C9: =SUM(C5:C8) -> -2156 | D9: =SUM(D5:D8) -> 84 | E9: =SUM(E5:E8) -> -453 | F9: =SUM(F5:F8) -> -2367 | G9: =SUM(G5:G8) -> 768 | H9: =SUM(H5:H8) -> -1424 | I9: =SUM(I5:I8) -> -6344 | J9: =SUM(J5:J8) -> -5082 | ... L9: =SUM(L5:L8) -> -2639
B10: Direct taxes | C10: -5653 | D10: -6829 | E10: -6832 | F10: -4550 | G10: -6389 | H10: -7612 | I10: -8794 | J10: -9231 | K10: -5602 | L10: -8648
B11: Cash-Flow from Operating Activity | C11: =SUM(C10,C9,C4,) -> 11531 | D11: =SUM(D10,D9,D4,) -> 13218 | E11: =SUM(E10,E9,E4,) -> 14841 | F11: =SUM(F10,F9,F4,) -> 17003 | G11: =SUM(G10,G9,G4,) -> 23224 | H11: =SUM(H10,H9,H4,) -> 23885 | I11: =SUM(I10,I9,I4,) -> 22467 | J11: =SUM(J10,J9,J4,) -> 25210 | ... L11: =SUM(L10,L9,L4,) -> 33986
B13: Cash from Investing Activity
B14: Fixed assets purchased | C14: -2760 | D14: -1998 | E14: -2445 | F14: -3307 | G14: -2107 | H14: -2161 | I14: -2579 | J14: -2201 | K14: -2237 | L14: -2727
B15: Investments purchased | C15: -66410 | D15: -69159 | E15: -79410 | F15: -37482 | G15: -46738 | H15: -59951 | I15: -75800 | J15: -78092 | K15: -82742 | L15: -82617
B16: Investments sold | C16: 52048 | D16: 74003 | E16: 78098 | F16: 38861 | G16: 40381 | H16: 57356 | I16: 76722 | J16: 72930 | K16: 84877 | L16: 89699
B17: Interest received | C17: 0 | D17: 0 | E17: 0 | F17: 0 | G17: 0 | H17: 0 | I17: 0 | J17: 0 | K17: 0 | L17: 0
B18: Dividends received | C18: 2753 | D18: 1768 | E18: 1557 | F18: 1929 | G18: 1418 | H18: 1898 | I18: 1525 | J18: 1768 | K18: 2040 | L18: 2713
B19: Acquisition of companies | C19: 0 | D19: 0 | E19: 0 | F19: 0 | G19: 0 | H19: 0 | I19: 0 | J19: 0 | K19: 0 | L19: 0
B20: Inter corporate deposits | C20: -164 | D20: -130 | E20: -24 | F20: -108 | G20: 0 | H20: 0 | I20: 0 | J20: 0 | K20: 0 | L20: 0
B21: Other investing items | C21: -131 | D21: 49 | E21: 1592 | F21: -224 | G21: -327 | H21: -3627 | I21: -939 | J21: 502 | K21: -3802 | L21: -3522
B22: Cash-Flow from Investing Activity | C22: =SUM(C14:C21) -> -14664 | D22: =SUM(D14:D21) -> 4533 | E22: =SUM(E14:E21) -> -632 | F22: =SUM(F14:F21) -> -331 | G22: =SUM(G14:G21) -> -7373 | H22: =SUM(H14:H21) -> -6485 | I22: =SUM(I14:I21) -> -1071 | J22: =SUM(J14:J21) -> -5093 | ... L22: =SUM(L14:L21) -> 3546
B24: Cash from Financing Activity
B25: Proceeds from shares | C25: 0 | D25: 5 | E25: 6 | F25: 6 | G25: 15 | H25: 21 | I25: 35 | J25: 5 | K25: 6 | L25: 2
B26: Repayment of borrowings | C26: 0 | D26: 0 | E26: 0 | F26: 0 | G26: 0 | H26: 0 | I26: 0 | J26: 0 | K26: -985 | L26: 0
B27: Dividends paid | C27: -6939 | D27: -7464 | E27: -13705 | F27: -9548 | G27: -9137 | H27: -12731 | I27: -13653 | J27: -14731 | K27: -20289 | L27: -18656
B28: Financial liabilities | C28: 0 | D28: 0 | E28: 0 | F28: -571 | G28: -698 | H28: -915 | I28: -1231 | J28: -2024 | K28: -2355 | L28: -2824
B29: Other financing items | C29: 0 | D29: -13046 | E29: -813 | F29: -7478 | G29: 34 | H29: -11017 | I29: -11846 | J29: -754 | K29: -538 | L29: -18308
B30: Cash-Flow from Financing Activity | C30: =SUM(C25:C29) -> -6939 | D30: =SUM(D25:D29) -> -20505 | E30: =SUM(E25:E29) -> -14512 | F30: =SUM(F25:F29) -> -17591 | G30: =SUM(G25:G29) -> -9786 | H30: =SUM(H25:H29) -> -24642 | I30: =SUM(I25:I29) -> -26695 | J30: =SUM(J25:J29) -> -17504 | ... L30: =SUM(L25:L29) -> -39786
B32: Net Cash Flow | C32: -10072 | D32: -2754 | E32: -303 | F32: -919 | G32: 6065 | H32: -7242 | I32: -5299 | J32: 2613 | K32: 9669 | L32: -2254
B36: Trade Payables | C36: 367 | D36: 694 | E36: 1655 | F36: 2852 | G36: 2645 | H36: 4134 | I36: 3865 | J36: 3956 | K36: 4164 | L36: 4744
B37: Advance from Customers | C37: 0 | D37: 0 | E37: 0 | F37: 0 | G37: 0 | H37: 0 | I37: 0 | J37: 0 | K37: 0 | L37: 0
